{
    "Input": "Analyze the month-over-month revenue generation trend for all products.",
    "Data_Summary": {
        "database_schema_sql": "CREATE TABLE \"data_asset_001_pcc\" (\n    `Cost_Efficiency` double, \n    `Date` text, \n    `Product` text, \n    `Product_Profitability` double, \n    `Revenue_Generation` int, \n    `Cost_Efficiency` double, \n    `Date` text, \n    `Product` text, \n    `Product_Profitability` double, \n    `Revenue_Generation` int(11)\n);",
        "table_description": "The \"data_asset_001_pcc\" table is a fact table that captures detailed financial data related to specific products, making it an essential resource for revenue and profitability analysis. It records cost efficiency, dates, product information, and product profitability, as well as revenue generation. This table is instrumental in evaluating product performance, enabling strategic decision-making for product development, pricing, and marketing. By offering comprehensive insights into financial metrics, it supports financial reporting, trend analysis, and forecasting, ultimately contributing to the overall financial health of the organization. This table contains transaction history data including the actual cost, modified date, product ID, quantity, reference order ID, reference order line ID, transaction date, transaction ID, and transaction type. Relevant KPIs that can be calculated from this table include customer segmentation by career and customer payment performance metrics such as accounts receivable aging report and average billing amount per customer.",
        "column_description": "Cost_Efficiency: Cost Efficiency is a metric that evaluates the performance of a product or process in terms of its cost relative to the output or revenue generated. \nDate: The Date column contains the dates for each month in the dataset, presented in the format: 'MM/DD/YYYY'. This column is used for organizing and tracking the data based on the date. \nProduct: The Product column specifies the product category, such as BroadBand, Entertainment, or Mobile, for which the cost efficiency, product profitability, and revenue generation are being measured. \nProduct_Profitability: Product Profitability is a measure of the profitability of a product, calculated by subtracting the product's costs from its revenue. \nRevenue_Generation: Revenue Generation is a measure of the total income generated by a product, calculated by multiplying the price of the product by the quantity sold. \nCost_Efficiency: Cost Efficiency represents the cost efficiency of a product, presented as a ratio. It is a measure of how well a company uses its resources in generating revenue. \nDate: The Date column contains the dates for each month in the dataset, presented in the format: 'MM/DD/YYYY'. This column is used for organizing and tracking the data based on the date. \nProduct: The Product column is a categorical variable that indicates the type of product. It includes BroadBand, Entertainment, and Mobile. \nProduct_Profitability: Product Profitability refers to the profitability of each product, presented as a ratio. It is a measure of how much profit is generated per product. \nRevenue_Generation: Revenue Generation indicates the revenue generated by each product, presented as a numerical value. It is used to determine the financial performance of each product. \n",
        "column_samples": "Cost_Efficiency: 8.008835757 \nDate: 01/01/2022 \nProduct: BroadBand \nProduct_Profitability: 0.052157515 \nRevenue_Generation: 61250 \nCost_Efficiency: 8.008835757 \nDate: 01/01/2022 \nProduct: BroadBand \nProduct_Profitability: 0.052157515 \nRevenue_Generation: 61250 \n",
        "sql_library": "MySQL",
        "database_properties": {
            "database_type": "mysql",
            "database_name": "datalake",
            "username": "AdaDB",
            "password": "Admin@2024",
            "hostname": "20.184.17.187",
            "port": 3306,
            "db_tag": "label1"
        },
        "column_name_list": [
            "Cost_Efficiency",
            "Date",
            "Product",
            "Product_Profitability",
            "Revenue_Generation",
            "Cost_Efficiency",
            "Date",
            "Product",
            "Product_Profitability",
            "Revenue_Generation",
            "",
            "",
            "",
            "",
            "",
            "",
            "",
            "",
            "",
            "",
            "",
            "",
            "",
            "",
            "",
            "",
            "",
            "",
            "",
            "",
            "",
            "",
            "",
            "",
            "",
            "",
            "",
            "",
            "",
            "",
            "",
            "",
            "",
            "",
            "",
            "",
            "",
            "",
            "",
            "",
            "",
            "",
            "",
            "",
            "",
            "",
            "",
            "",
            "",
            "",
            "",
            "",
            "",
            "",
            "",
            "",
            "",
            "",
            "",
            "",
            "",
            "",
            "",
            "",
            "",
            "",
            "",
            "",
            "",
            "",
            "",
            "",
            "",
            "",
            "",
            "",
            "",
            "",
            "",
            "",
            "",
            "",
            "",
            ""
        ],
        "column_display_names": "Cost_Efficiency: Cost Efficiency \nDate: Date \nProduct: Product \nProduct_Profitability: Product Profitability \nRevenue_Generation: Revenue Generation \nCost_Efficiency: Cost Efficiency \nDate: Date \nProduct: Product \nProduct_Profitability: Product Profitability \nRevenue_Generation: Revenue Generation \n",
        "column_data_tribes": {
            "Cost_Efficiency": "numerical",
            "Date": "date_related",
            "Product": "categorical",
            "Product_Profitability": "numerical",
            "Revenue_Generation": "numerical"
        },
        "column_sql_data_types": {
            "Cost_Efficiency": "double",
            "Date": "text",
            "Product": "text",
            "Product_Profitability": "double",
            "Revenue_Generation": "int(11)"
        },
        "table_join_sql_query": ""
    },
    "Story_Skeleton": "StoryNarrative(narrative='To analyze the month-over-month revenue generation trend for all products, we need to examine the revenue generated by each product over time. This will help us understand the financial performance of each product and identify any trends or patterns in revenue generation. We can start by looking at the total revenue generated by all products over the past year, and then break it down by product category to see which ones are performing well. Additionally, we can analyze the cost efficiency and product profitability of each product to see how they impact revenue generation. By examining these metrics, we can gain a deeper understanding of the revenue generation trend for all products and make informed decisions to drive business growth.', main_questions=[{'main_question': 'What is the total revenue generated by all products over the past year?', 'main_title': 'Total Revenue Generation Over Past Year', 'main_chart_type': 'line_chart', 'sub_questions': [{'question': 'What is the average month-over-month growth rate for all products revenue in the past year?', 'chart_title': 'Average Month-over-Month Growth Rate for All Products Revenue (Past Year)', 'chart_type': 'spline_chart', 'chart_axis': {'xAxis_title': 'Month', 'xAxis_column': 'Date', 'yAxis_title': 'Total Revenue Generation', 'yAxis_column': 'Revenue_Generation', 'yAxis_aggregation': 'SUM', 'yAxis2_title': '', 'yAxis2_column': '', 'yAxis2_aggregation': '', 'yAxis3_title': '', 'yAxis3_column': '', 'yAxis3_aggregation': '', 'series_title': '', 'series_column': ''}, 'chart_sql': \"SELECT CONCAT(YEAR(STR_TO_DATE(Date, '%m/%d/%Y')), '-', MONTH(STR_TO_DATE(Date, '%m/%d/%Y'))) AS xAxis, AVG((SUM(Revenue_Generation) - LAG(SUM(Revenue_Generation), 1, 0) OVER (ORDER BY STR_TO_DATE(Date, '%m/%d/%Y'))) / LAG(SUM(Revenue_Generation), 1, 0) OVER (ORDER BY STR_TO_DATE(Date, '%m/%d/%Y'))) AS yAxis FROM starhub_data_asset.data_asset_001_pcc WHERE STR_TO_DATE(Date, '%m/%d/%Y') BETWEEN DATE_SUB(CURDATE(), INTERVAL 1 YEAR) AND CURDATE() GROUP BY xAxis ORDER BY xAxis;\", 'chart_data': Empty DataFrame\nColumns: []\nIndex: []}, {'question': 'What is the total revenue generated by all products in each quarter of the past year?', 'chart_title': 'Total Revenue Generated by All Products (Quarterly, Past Year)', 'chart_type': 'bar_chart', 'chart_axis': {'xAxis_title': 'Quarter', 'xAxis_column': 'Date', 'yAxis_title': 'Total Revenue', 'yAxis_column': 'Revenue_Generation', 'yAxis_aggregation': 'SUM'}, 'chart_sql': \"SELECT CONCAT(YEAR(STR_TO_DATE(Date, '%d/%m/%Y')), '-Q', QUARTER(STR_TO_DATE(Date, '%d/%m/%Y'))) AS xAxis, SUM(Revenue_Generation) AS yAxis FROM data_asset_001_pcc WHERE STR_TO_DATE(Date, '%d/%m/%Y') BETWEEN DATE_SUB(CURDATE(), INTERVAL 1 YEAR) AND CURDATE() GROUP BY xAxis ORDER BY xAxis;\", 'chart_data': Empty DataFrame\nColumns: []\nIndex: []}, {'question': 'What is the monthly total revenue generated by all products over the past year?', 'chart_title': 'Monthly Total Revenue Generated by All Products (Past Year)', 'chart_type': 'line_chart', 'chart_axis': {'xAxis_title': 'Month', 'xAxis_column': 'Date', 'yAxis_title': 'Total Revenue', 'yAxis_column': 'Revenue_Generation', 'yAxis_aggregation': 'SUM', 'yAxis2_title': '', 'yAxis2_column': '', 'yAxis2_aggregation': '', 'yAxis3_title': '', 'yAxis3_column': '', 'yAxis3_aggregation': '', 'series_title': '', 'series_column': ''}, 'chart_sql': \"SELECT CONCAT(YEAR(STR_TO_DATE(Date, '%m/%d/%Y')), '-', MONTH(STR_TO_DATE(Date, '%m/%d/%Y'))) AS xAxis, SUM(Revenue_Generation) AS yAxis FROM starhub_data_asset.data_asset_001_pcc WHERE STR_TO_DATE(Date, '%m/%d/%Y') BETWEEN DATE_SUB(CURDATE(), INTERVAL 1 YEAR) AND CURDATE() GROUP BY CONCAT(YEAR(STR_TO_DATE(Date, '%m/%d/%Y')), '-', MONTH(STR_TO_DATE(Date, '%m/%d/%Y'))) ORDER BY CONCAT(YEAR(STR_TO_DATE(Date, '%m/%d/%Y')), '-', MONTH(STR_TO_DATE(Date, '%m/%d/%Y')));\", 'chart_data': Empty DataFrame\nColumns: [xAxis, yAxis]\nIndex: []}], 'overall_title': {'overarching_title': 'Revenue Performance and Growth Trends'}, 'main_chart_axis': {'xAxis_title': 'Month', 'xAxis_column': 'Date', 'yAxis_title': 'Total Revenue Generation', 'yAxis_column': 'Revenue_Generation', 'yAxis_aggregation': 'SUM', 'yAxis2_title': '', 'yAxis2_column': '', 'yAxis2_aggregation': '', 'yAxis3_title': '', 'yAxis3_column': '', 'yAxis3_aggregation': '', 'series_title': '', 'series_column': ''}, 'main_chart_sql': \"SELECT CONCAT(YEAR(STR_TO_DATE(`Date`, '%m/%d/%Y')), '-', MONTH(STR_TO_DATE(`Date`, '%m/%d/%Y'))) AS xAxis, SUM(`Revenue_Generation`) AS yAxis FROM data_asset_001_pcc WHERE STR_TO_DATE(`Date`, '%m/%d/%Y') BETWEEN DATE_SUB(CURDATE(), INTERVAL 1 YEAR) AND CURDATE() GROUP BY xAxis ORDER BY xAxis;\", 'chart_data': Empty DataFrame\nColumns: []\nIndex: []}, {'main_question': 'How does the revenue generation trend vary by product category?', 'main_title': 'Monthly Revenue Generation by Product Category', 'main_chart_type': 'grouped_bar_chart', 'sub_questions': [{'question': 'What is the monthly total revenue generation trend for each product in the past year?', 'chart_title': 'Monthly Total Revenue Generation Trend by Product (Past Year)', 'chart_type': 'grouped_column_chart', 'chart_axis': {'xAxis_title': 'Month', 'xAxis_column': 'Date', 'yAxis_title': 'Total Revenue Generation', 'yAxis_column': 'Revenue_Generation', 'yAxis_aggregation': 'SUM', 'yAxis2_title': '', 'yAxis2_column': '', 'yAxis2_aggregation': '', 'yAxis3_title': '', 'yAxis3_column': '', 'yAxis3_aggregation': '', 'series_title': 'Product', 'series_column': 'Product'}, 'chart_sql': \"SELECT CONCAT(YEAR(STR_TO_DATE(Date, '%d/%m/%Y')), '-', MONTH(STR_TO_DATE(Date, '%d/%m/%Y'))) AS xAxis, SUM(Revenue_Generation) AS yAxis, Product AS series FROM starhub_data_asset.data_asset_001_pcc WHERE STR_TO_DATE(Date, '%d/%m/%Y') BETWEEN DATE_SUB(CURDATE(), INTERVAL 1 YEAR) AND CURDATE() GROUP BY xAxis, series ORDER BY xAxis;\", 'chart_data':       xAxis         series      yAxis\n0   2023-10      BroadBand  2743715.0\n1   2023-10  Entertainment  2585464.0\n2   2023-10         Mobile  2911653.0\n3   2023-11      BroadBand  3278994.0\n4   2023-11  Entertainment  3089869.0\n5   2023-11         Mobile  3479695.0\n6   2023-12      BroadBand  3918701.0\n7   2023-12  Entertainment  3692680.0\n8   2023-12         Mobile  4158557.0\n9    2023-9      BroadBand  2295818.0\n10   2023-9  Entertainment  2163401.0\n11   2023-9         Mobile  2436341.0, 'chart_json': {'Subscription_ID': '', 'Subscription_Name': '', 'Client_ID': 'starhub_001', 'User_ID': 'goldius.leo@userdata.tech', 'Shared_User_ID': '', 'Chart_Name': 'Visual 1', 'Visual_Title': {'overarching_title': 'Revenue Trends by Product Category Analysis'}, 'Chart_Axis': {'xAxis_title': 'Month', 'xAxis_column': 'Date', 'yAxis_title': 'Total Revenue Generation', 'yAxis_column': 'Revenue_Generation', 'yAxis_aggregation': 'SUM', 'yAxis2_title': '', 'yAxis2_column': '', 'yAxis2_aggregation': '', 'yAxis3_title': '', 'yAxis3_column': '', 'yAxis3_aggregation': '', 'series_title': 'Product', 'series_column': 'Product'}, 'Chart_Query': \"SELECT CONCAT(YEAR(STR_TO_DATE(Date, '%d/%m/%Y')), '-', MONTH(STR_TO_DATE(Date, '%d/%m/%Y'))) AS xAxis, SUM(Revenue_Generation) AS yAxis, Product AS series FROM starhub_data_asset.data_asset_001_pcc WHERE STR_TO_DATE(Date, '%d/%m/%Y') BETWEEN DATE_SUB(CURDATE(), INTERVAL 1 YEAR) AND CURDATE() GROUP BY xAxis, series ORDER BY xAxis;\", 'Chart_SQL_Library': 'MySQL', 'Chart_Position': '1', 'Chart_Type': 'grouped_column_chart', 'Chart_Title': 'Monthly Total Revenue Generation Trend by Product (Past Year)', 'xAxis': 'Month', 'xAxis_Description': 'Month', 'X': ['2023-9', '2023-10', '2023-11', '2023-12'], 'yAxis': 'Total Revenue Generation', 'yAxis_Description': 'Total Revenue Generation', 'Y': [2295818.0, 2743715.0, 3278994.0, 3918701.0], 'Y2': [2163401.0, 2585464.0, 3089869.0, 3692680.0], 'Y3': [2436341.0, 2911653.0, 3479695.0, 4158557.0], 'yName': 'Total Revenue Generation (BroadBand)', 'y2Name': 'Total Revenue Generation (Entertainment)', 'y3Name': 'Total Revenue Generation (Mobile)', 'Smart_Insight': 'No Description', 'Business_Insight': 'No Description', 'Aggregated_Table_JSON': {'Subscription_ID': '', 'Subscription_Name': '', 'Client_ID': 'starhub_001', 'User_ID': 'goldius.leo@userdata.tech', 'Shared_User_ID': '', 'Chart_Name': 'Visual 1', 'Chart_Axis': {}, 'Chart_Query': \"SELECT CONCAT(YEAR(STR_TO_DATE(Date, '%d/%m/%Y')), '-', MONTH(STR_TO_DATE(Date, '%d/%m/%Y'))) AS xAxis, SUM(Revenue_Generation) AS yAxis, Product AS series FROM starhub_data_asset.data_asset_001_pcc WHERE STR_TO_DATE(Date, '%d/%m/%Y') BETWEEN DATE_SUB(CURDATE(), INTERVAL 1 YEAR) AND CURDATE() GROUP BY xAxis, series ORDER BY xAxis;\", 'Chart_SQL_Library': 'MySQL', 'Chart_Position': '1', 'Chart_Type': 'aggregated_table_chart', 'Chart_Size': 184, 'data': [{'Month': '2023-9', 'Product': 'BroadBand', 'Total Revenue Generation': 2295818.0}, {'Month': '2023-9', 'Product': 'Entertainment', 'Total Revenue Generation': 2163401.0}, {'Month': '2023-9', 'Product': 'Mobile', 'Total Revenue Generation': 2436341.0}, {'Month': '2023-10', 'Product': 'BroadBand', 'Total Revenue Generation': 2743715.0}, {'Month': '2023-10', 'Product': 'Entertainment', 'Total Revenue Generation': 2585464.0}, {'Month': '2023-10', 'Product': 'Mobile', 'Total Revenue Generation': 2911653.0}, {'Month': '2023-11', 'Product': 'BroadBand', 'Total Revenue Generation': 3278994.0}, {'Month': '2023-11', 'Product': 'Entertainment', 'Total Revenue Generation': 3089869.0}, {'Month': '2023-11', 'Product': 'Mobile', 'Total Revenue Generation': 3479695.0}, {'Month': '2023-12', 'Product': 'BroadBand', 'Total Revenue Generation': 3918701.0}, {'Month': '2023-12', 'Product': 'Entertainment', 'Total Revenue Generation': 3692680.0}, {'Month': '2023-12', 'Product': 'Mobile', 'Total Revenue Generation': 4158557.0}], 'Smart_Insight': 'No Description', 'Business_Insight': 'No Description', 'Database_Properties': {'database_type': 'mysql', 'database_name': 'datalake', 'username': 'AdaDB', 'password': 'Admin@2024', 'hostname': '20.184.17.187', 'port': 3306, 'db_tag': 'label1'}}, 'Aggregated_Table_Column': ['Revenue_Generation', 'Product', 'Date'], 'Database_Properties': {'database_type': 'mysql', 'database_name': 'datalake', 'username': 'AdaDB', 'password': 'Admin@2024', 'hostname': '20.184.17.187', 'port': 3306, 'db_tag': 'label1'}}}, {'question': 'What is the average month-over-month growth rate for each product category over the past two years?', 'chart_title': 'Average Month-over-Month Growth Rate by Product Category (Past Two Years)', 'chart_type': 'spline_chart', 'chart_axis': {'xAxis_title': 'Month', 'xAxis_column': 'Date', 'yAxis_title': 'Total Revenue Generation', 'yAxis_column': 'Revenue_Generation', 'yAxis_aggregation': 'SUM', 'yAxis2_title': '', 'yAxis2_column': '', 'yAxis2_aggregation': '', 'yAxis3_title': '', 'yAxis3_column': '', 'yAxis3_aggregation': '', 'series_title': 'Product', 'series_column': 'Product'}, 'chart_sql': \"SELECT CONCAT(YEAR(STR_TO_DATE(`Date`, '%m/%d/%Y')), '-', MONTH(STR_TO_DATE(`Date`, '%m/%d/%Y'))) AS xAxis, `Product` AS series, AVG((`Revenue_Generation` - LAG(`Revenue_Generation`) OVER (PARTITION BY `Product` ORDER BY STR_TO_DATE(`Date`, '%m/%d/%Y'))) / LAG(`Revenue_Generation`) OVER (PARTITION BY `Product` ORDER BY STR_TO_DATE(`Date`, '%m/%d/%Y'))) AS yAxis FROM data_asset_001_pcc WHERE STR_TO_DATE(`Date`, '%m/%d/%Y') BETWEEN DATE_SUB(CURDATE(), INTERVAL 2 YEAR) AND CURDATE() GROUP BY xAxis, series ORDER BY xAxis;\", 'chart_data': Empty DataFrame\nColumns: []\nIndex: []}, {'question': 'What is the total revenue generation for each product category in the past quarter?', 'chart_title': 'Total Revenue Generation by Product Category (Past Quarter)', 'chart_type': 'bar_chart', 'chart_axis': {'xAxis_title': 'Product Category', 'xAxis_column': 'Product', 'yAxis_title': 'Total Revenue Generation', 'yAxis_column': 'Revenue_Generation', 'yAxis_aggregation': 'SUM'}, 'chart_sql': \"SELECT `Product` AS xAxis, SUM(`Revenue_Generation`) AS yAxis FROM starhub_data_asset.data_asset_001_pcc WHERE STR_TO_DATE(`Date`, '%m/%d/%Y') BETWEEN DATE_SUB(CURDATE(), INTERVAL 1 QUARTER) AND CURDATE() GROUP BY xAxis ORDER BY xAxis;\", 'chart_data': Empty DataFrame\nColumns: [xAxis, yAxis]\nIndex: []}], 'overall_title': {'overarching_title': 'Revenue Trends by Product Category Analysis'}, 'main_chart_axis': {'xAxis_title': 'Month', 'xAxis_column': 'Date', 'yAxis_title': 'Total Revenue Generation', 'yAxis_column': 'Revenue_Generation', 'yAxis_aggregation': 'SUM', 'yAxis2_title': '', 'yAxis2_column': '', 'yAxis2_aggregation': '', 'yAxis3_title': '', 'yAxis3_column': '', 'yAxis3_aggregation': '', 'series_title': 'Product Category', 'series_column': 'Product'}, 'main_chart_sql': \"SELECT CONCAT(YEAR(STR_TO_DATE(`Date`, '%m/%d/%Y')), '-', MONTH(STR_TO_DATE(`Date`, '%m/%d/%Y'))) AS xAxis, SUM(`Revenue_Generation`) AS yAxis, `Product` AS series FROM data_asset_001_pcc WHERE STR_TO_DATE(`Date`, '%m/%d/%Y') >= DATE_SUB(CURDATE(), INTERVAL 1 YEAR) AND STR_TO_DATE(`Date`, '%m/%d/%Y') <= CURDATE() GROUP BY xAxis, series ORDER BY xAxis;\", 'chart_data': Empty DataFrame\nColumns: [xAxis, yAxis, series]\nIndex: []}, {'main_question': 'What is the average cost efficiency of all products over the past year?', 'main_title': 'Average Cost Efficiency Over Past Year', 'main_chart_type': 'line_chart', 'sub_questions': [{'question': 'What is the total revenue generation for all products over the past year?', 'chart_title': 'Total Revenue Generation for All Products Past Year', 'chart_type': 'bar_chart', 'chart_axis': {'xAxis_title': 'Product', 'xAxis_column': 'Product', 'yAxis_title': 'Total Revenue Generation', 'yAxis_column': 'Revenue_Generation', 'yAxis_aggregation': 'SUM'}, 'chart_sql': \"SELECT `Product` AS xAxis, SUM(`Revenue_Generation`) AS yAxis FROM starhub_data_asset.data_asset_001_pcc WHERE STR_TO_DATE(`Date`, '%m/%d/%Y') BETWEEN DATE_SUB(CURDATE(), INTERVAL 1 YEAR) AND CURDATE() GROUP BY xAxis ORDER BY xAxis;\", 'chart_data': Empty DataFrame\nColumns: [xAxis, yAxis]\nIndex: []}, {'question': 'What is the monthly average revenue generation trend for all products over the past year?', 'chart_title': 'Monthly Average Revenue Generation Trend for All Products Past Year', 'chart_type': 'line_chart', 'chart_axis': {'xAxis_title': 'Month', 'xAxis_column': 'Date', 'yAxis_title': 'Average Revenue Generation', 'yAxis_column': 'Revenue_Generation', 'yAxis_aggregation': 'AVG', 'yAxis2_title': '', 'yAxis2_column': '', 'yAxis2_aggregation': '', 'yAxis3_title': '', 'yAxis3_column': '', 'yAxis3_aggregation': '', 'series_title': '', 'series_column': ''}, 'chart_sql': \"SELECT CONCAT(YEAR(STR_TO_DATE(Date, '%d/%m/%Y')), '-', MONTH(STR_TO_DATE(Date, '%d/%m/%Y'))) AS xAxis, AVG(Revenue_Generation) AS yAxis FROM data_asset_001_pcc WHERE STR_TO_DATE(Date, '%d/%m/%Y') BETWEEN DATE_SUB(CURDATE(), INTERVAL 1 YEAR) AND CURDATE() GROUP BY CONCAT(YEAR(STR_TO_DATE(Date, '%d/%m/%Y')), '-', MONTH(STR_TO_DATE(Date, '%d/%m/%Y'))) ORDER BY CONCAT(YEAR(STR_TO_DATE(Date, '%d/%m/%Y')), '-', MONTH(STR_TO_DATE(Date, '%d/%m/%Y')));\", 'chart_data': Empty DataFrame\nColumns: []\nIndex: []}, {'question': 'What is the product-wise distribution of average revenue generation over the past year?', 'chart_title': 'Product-wise Distribution of Average Revenue Generation Past Year', 'chart_type': 'grouped_bar_chart', 'chart_axis': {'xAxis_title': 'Product', 'xAxis_column': 'Product', 'yAxis_title': 'Average Revenue Generation', 'yAxis_column': 'Revenue_Generation', 'yAxis_aggregation': 'AVG', 'yAxis2_title': '', 'yAxis2_column': '', 'yAxis2_aggregation': '', 'yAxis3_title': '', 'yAxis3_column': '', 'yAxis3_aggregation': '', 'series_title': '', 'series_column': ''}, 'chart_sql': \"SELECT `Product` AS xAxis, AVG(`Revenue_Generation`) AS yAxis FROM starhub_data_asset.data_asset_001_pcc WHERE STR_TO_DATE(`Date`, '%m/%d/%Y') BETWEEN DATE_SUB(CURDATE(), INTERVAL 1 YEAR) AND CURDATE() GROUP BY xAxis ORDER BY xAxis;\", 'chart_data': Empty DataFrame\nColumns: [xAxis, yAxis]\nIndex: []}], 'overall_title': {'overarching_title': 'Revenue and Cost Efficiency Analysis Over Past Year'}, 'main_chart_axis': {'xAxis_title': 'Month', 'xAxis_column': 'Date', 'yAxis_title': 'Average Cost Efficiency', 'yAxis_column': 'Cost_Efficiency', 'yAxis_aggregation': 'AVG', 'yAxis2_title': '', 'yAxis2_column': '', 'yAxis2_aggregation': '', 'yAxis3_title': '', 'yAxis3_column': '', 'yAxis3_aggregation': '', 'series_title': '', 'series_column': ''}, 'main_chart_sql': \"SELECT CONCAT(YEAR(STR_TO_DATE(`Date`, '%m/%d/%Y')), '-', MONTH(STR_TO_DATE(`Date`, '%m/%d/%Y'))) AS xAxis, AVG(`Cost_Efficiency`) AS yAxis FROM data_asset_001_pcc WHERE STR_TO_DATE(`Date`, '%m/%d/%Y') BETWEEN DATE_SUB(CURDATE(), INTERVAL 1 YEAR) AND CURDATE() GROUP BY xAxis ORDER BY xAxis;\", 'chart_data': Empty DataFrame\nColumns: [xAxis, yAxis]\nIndex: []}, {'main_question': 'How does the product profitability vary by product category?', 'main_title': 'Average Product Profitability by Product Category', 'main_chart_type': 'bar_chart', 'sub_questions': [{'question': 'What is the monthly total revenue generation trend for each product in the past year?', 'chart_title': 'Monthly Total Revenue Generation Trend by Product (Past Year)', 'chart_type': 'grouped_column_chart', 'chart_axis': {'xAxis_title': 'Month', 'xAxis_column': 'Date', 'yAxis_title': 'Total Revenue Generation', 'yAxis_column': 'Revenue_Generation', 'yAxis_aggregation': 'SUM', 'yAxis2_title': '', 'yAxis2_column': '', 'yAxis2_aggregation': '', 'yAxis3_title': '', 'yAxis3_column': '', 'yAxis3_aggregation': '', 'series_title': 'Product', 'series_column': 'Product'}, 'chart_sql': \"SELECT CONCAT(YEAR(STR_TO_DATE(Date, '%d/%m/%Y')), '-', MONTH(STR_TO_DATE(Date, '%d/%m/%Y'))) AS xAxis, SUM(Revenue_Generation) AS yAxis, Product AS series FROM starhub_data_asset.data_asset_001_pcc WHERE STR_TO_DATE(Date, '%d/%m/%Y') BETWEEN DATE_SUB(CURDATE(), INTERVAL 1 YEAR) AND CURDATE() GROUP BY xAxis, series ORDER BY xAxis;\", 'chart_data':       xAxis         series      yAxis\n0   2023-10      BroadBand  2743715.0\n1   2023-10  Entertainment  2585464.0\n2   2023-10         Mobile  2911653.0\n3   2023-11      BroadBand  3278994.0\n4   2023-11  Entertainment  3089869.0\n5   2023-11         Mobile  3479695.0\n6   2023-12      BroadBand  3918701.0\n7   2023-12  Entertainment  3692680.0\n8   2023-12         Mobile  4158557.0\n9    2023-9      BroadBand  2295818.0\n10   2023-9  Entertainment  2163401.0\n11   2023-9         Mobile  2436341.0, 'chart_json': {'Subscription_ID': '', 'Subscription_Name': '', 'Client_ID': 'starhub_001', 'User_ID': 'goldius.leo@userdata.tech', 'Shared_User_ID': '', 'Chart_Name': 'Visual 2', 'Chart_Axis': {'xAxis_title': 'Month', 'xAxis_column': 'Date', 'yAxis_title': 'Total Revenue Generation', 'yAxis_column': 'Revenue_Generation', 'yAxis_aggregation': 'SUM', 'yAxis2_title': '', 'yAxis2_column': '', 'yAxis2_aggregation': '', 'yAxis3_title': '', 'yAxis3_column': '', 'yAxis3_aggregation': '', 'series_title': 'Product', 'series_column': 'Product'}, 'Chart_Query': \"SELECT CONCAT(YEAR(STR_TO_DATE(Date, '%d/%m/%Y')), '-', MONTH(STR_TO_DATE(Date, '%d/%m/%Y'))) AS xAxis, SUM(Revenue_Generation) AS yAxis, Product AS series FROM starhub_data_asset.data_asset_001_pcc WHERE STR_TO_DATE(Date, '%d/%m/%Y') BETWEEN DATE_SUB(CURDATE(), INTERVAL 1 YEAR) AND CURDATE() GROUP BY xAxis, series ORDER BY xAxis;\", 'Chart_SQL_Library': 'MySQL', 'Chart_Position': '2', 'Chart_Type': 'grouped_column_chart', 'Chart_Title': 'Monthly Total Revenue Generation Trend by Product (Past Year)', 'xAxis': 'Month', 'xAxis_Description': 'Month', 'X': ['2023-9', '2023-10', '2023-11', '2023-12'], 'yAxis': 'Total Revenue Generation', 'yAxis_Description': 'Total Revenue Generation', 'Y': [2295818.0, 2743715.0, 3278994.0, 3918701.0], 'Y2': [2163401.0, 2585464.0, 3089869.0, 3692680.0], 'Y3': [2436341.0, 2911653.0, 3479695.0, 4158557.0], 'yName': 'Total Revenue Generation (BroadBand)', 'y2Name': 'Total Revenue Generation (Entertainment)', 'y3Name': 'Total Revenue Generation (Mobile)', 'Smart_Insight': 'No Description', 'Business_Insight': 'No Description', 'Aggregated_Table_JSON': {'Subscription_ID': '', 'Subscription_Name': '', 'Client_ID': 'starhub_001', 'User_ID': 'goldius.leo@userdata.tech', 'Shared_User_ID': '', 'Chart_Name': 'Visual 2', 'Chart_Axis': {}, 'Chart_Query': \"SELECT CONCAT(YEAR(STR_TO_DATE(Date, '%d/%m/%Y')), '-', MONTH(STR_TO_DATE(Date, '%d/%m/%Y'))) AS xAxis, SUM(Revenue_Generation) AS yAxis, Product AS series FROM starhub_data_asset.data_asset_001_pcc WHERE STR_TO_DATE(Date, '%d/%m/%Y') BETWEEN DATE_SUB(CURDATE(), INTERVAL 1 YEAR) AND CURDATE() GROUP BY xAxis, series ORDER BY xAxis;\", 'Chart_SQL_Library': 'MySQL', 'Chart_Position': '2', 'Chart_Type': 'aggregated_table_chart', 'Chart_Size': 184, 'data': [{'Month': '2023-9', 'Product': 'BroadBand', 'Total Revenue Generation': 2295818.0}, {'Month': '2023-9', 'Product': 'Entertainment', 'Total Revenue Generation': 2163401.0}, {'Month': '2023-9', 'Product': 'Mobile', 'Total Revenue Generation': 2436341.0}, {'Month': '2023-10', 'Product': 'BroadBand', 'Total Revenue Generation': 2743715.0}, {'Month': '2023-10', 'Product': 'Entertainment', 'Total Revenue Generation': 2585464.0}, {'Month': '2023-10', 'Product': 'Mobile', 'Total Revenue Generation': 2911653.0}, {'Month': '2023-11', 'Product': 'BroadBand', 'Total Revenue Generation': 3278994.0}, {'Month': '2023-11', 'Product': 'Entertainment', 'Total Revenue Generation': 3089869.0}, {'Month': '2023-11', 'Product': 'Mobile', 'Total Revenue Generation': 3479695.0}, {'Month': '2023-12', 'Product': 'BroadBand', 'Total Revenue Generation': 3918701.0}, {'Month': '2023-12', 'Product': 'Entertainment', 'Total Revenue Generation': 3692680.0}, {'Month': '2023-12', 'Product': 'Mobile', 'Total Revenue Generation': 4158557.0}], 'Smart_Insight': 'No Description', 'Business_Insight': 'No Description', 'Database_Properties': {'database_type': 'mysql', 'database_name': 'datalake', 'username': 'AdaDB', 'password': 'Admin@2024', 'hostname': '20.184.17.187', 'port': 3306, 'db_tag': 'label1'}}, 'Aggregated_Table_Column': ['Revenue_Generation', 'Product', 'Date'], 'Database_Properties': {'database_type': 'mysql', 'database_name': 'datalake', 'username': 'AdaDB', 'password': 'Admin@2024', 'hostname': '20.184.17.187', 'port': 3306, 'db_tag': 'label1'}}}, {'question': 'What is the average month-over-month growth rate for all products revenue in the past two years?', 'chart_title': 'Average Month-over-Month Growth Rate for All Products Revenue (Past Two Years)', 'chart_type': 'spline_chart', 'chart_axis': {'xAxis_title': 'Month', 'xAxis_column': 'Date', 'yAxis_title': 'Total Revenue Generation', 'yAxis_column': 'Revenue_Generation', 'yAxis_aggregation': 'SUM', 'yAxis2_title': '', 'yAxis2_column': '', 'yAxis2_aggregation': '', 'yAxis3_title': '', 'yAxis3_column': '', 'yAxis3_aggregation': '', 'series_title': 'Product', 'series_column': 'Product'}, 'chart_sql': \"SELECT CONCAT(YEAR(STR_TO_DATE(`Date`, '%m/%d/%Y')), '-', MONTH(STR_TO_DATE(`Date`, '%m/%d/%Y'))) AS xAxis, AVG((`Revenue_Generation` - LAG(`Revenue_Generation`) OVER (PARTITION BY `Product` ORDER BY STR_TO_DATE(`Date`, '%m/%d/%Y'))) / LAG(`Revenue_Generation`) OVER (PARTITION BY `Product` ORDER BY STR_TO_DATE(`Date`, '%m/%d/%Y'))) AS yAxis, `Product` AS series FROM data_asset_001_pcc WHERE STR_TO_DATE(`Date`, '%m/%d/%Y') BETWEEN DATE_SUB(CURDATE(), INTERVAL 2 YEAR) AND CURDATE() GROUP BY xAxis, series ORDER BY xAxis;\", 'chart_data': Empty DataFrame\nColumns: []\nIndex: []}, {'question': 'What is the distribution of monthly revenue generation for all products over the past year?', 'chart_title': 'Distribution of Monthly Revenue Generation for All Products (Past Year)', 'chart_type': 'histogram_chart', 'chart_axis': {'xAxis_title': 'Monthly Revenue Generation', 'xAxis_column': 'Revenue_Generation'}, 'chart_sql': \"SELECT `Revenue_Generation` AS xAxis FROM data_asset_001_pcc WHERE STR_TO_DATE(`Date`, '%m/%d/%Y') BETWEEN DATE_SUB(CURDATE(), INTERVAL 1 YEAR) AND CURDATE() GROUP BY xAxis ORDER BY xAxis;\", 'chart_data': Empty DataFrame\nColumns: []\nIndex: []}], 'overall_title': {'overarching_title': 'Product Profitability and Revenue Trends Analysis'}, 'main_chart_axis': {'xAxis_title': 'Product Category', 'xAxis_column': 'Product', 'yAxis_title': 'Average Product Profitability', 'yAxis_column': 'Product_Profitability', 'yAxis_aggregation': 'AVG'}, 'main_chart_sql': 'SELECT `Product` AS xAxis, AVG(`Product_Profitability`) AS yAxis FROM starhub_data_asset.data_asset_001_pcc GROUP BY `Product` ORDER BY xAxis;', 'chart_data':            xAxis     yAxis\n0      BroadBand  0.796062\n1  Entertainment  0.841979\n2         Mobile  0.748757, 'main_chart_json': {'Subscription_ID': '', 'Subscription_Name': '', 'Client_ID': 'starhub_001', 'User_ID': 'goldius.leo@userdata.tech', 'Shared_User_ID': '', 'Chart_Name': 'Visual 2', 'Visual_Title': {'overarching_title': 'Product Profitability and Revenue Trends Analysis'}, 'Chart_Axis': {'xAxis_title': 'Product Category', 'xAxis_column': 'Product', 'yAxis_title': 'Average Product Profitability', 'yAxis_column': 'Product_Profitability', 'yAxis_aggregation': 'AVG'}, 'Chart_Query': 'SELECT `Product` AS xAxis, AVG(`Product_Profitability`) AS yAxis FROM starhub_data_asset.data_asset_001_pcc GROUP BY `Product` ORDER BY xAxis;', 'Chart_SQL_Library': 'MySQL', 'Chart_Position': '1', 'Chart_Type': 'bar_chart', 'Chart_Title': 'Average Product Profitability by Product Category', 'xAxis': 'Product Category', 'xAxis_Description': 'Product Category', 'X': ['BroadBand', 'Entertainment', 'Mobile'], 'yAxis': 'Average Product Profitability', 'yAxis_Description': 'Average Product Profitability', 'Y': [0.7960617916666667, 0.84197925, 0.7487574583333333], 'Smart_Insight': 'No Description', 'Business_Insight': 'No Description', 'Aggregated_Table_JSON': {'Subscription_ID': '', 'Subscription_Name': '', 'Client_ID': 'starhub_001', 'User_ID': 'goldius.leo@userdata.tech', 'Shared_User_ID': '', 'Chart_Name': 'Visual 2', 'Chart_Axis': {}, 'Chart_Query': 'SELECT `Product` AS xAxis, AVG(`Product_Profitability`) AS yAxis FROM starhub_data_asset.data_asset_001_pcc GROUP BY `Product` ORDER BY xAxis;', 'Chart_SQL_Library': 'MySQL', 'Chart_Position': '1', 'Chart_Type': 'aggregated_table_chart', 'Chart_Size': 88, 'data': [{'Product Category': 'BroadBand', 'Average Product Profitability': 0.7960617916666667}, {'Product Category': 'Entertainment', 'Average Product Profitability': 0.84197925}, {'Product Category': 'Mobile', 'Average Product Profitability': 0.7487574583333333}], 'Smart_Insight': 'No Description', 'Business_Insight': 'No Description', 'Database_Properties': {'database_type': 'mysql', 'database_name': 'datalake', 'username': 'AdaDB', 'password': 'Admin@2024', 'hostname': '20.184.17.187', 'port': 3306, 'db_tag': 'label1'}}, 'Aggregated_Table_Column': ['Product', 'Product_Profitability'], 'Database_Properties': {'database_type': 'mysql', 'database_name': 'datalake', 'username': 'AdaDB', 'password': 'Admin@2024', 'hostname': '20.184.17.187', 'port': 3306, 'db_tag': 'label1'}, 'yName': 'Average Product Profitability'}}, {'main_question': 'What is the month-over-month revenue growth rate for each product category?', 'main_title': 'Month-over-Month Revenue Growth Rate by Product Category', 'main_chart_type': 'spline_chart', 'sub_questions': [{'question': 'What is the total revenue generation for each product category over the past year?', 'chart_title': 'Total Revenue Generation by Product Category Past Year', 'chart_type': 'bar_chart'}, {'question': 'What is the average monthly revenue generation for each product category in the past two years?', 'chart_title': 'Average Monthly Revenue Generation by Product Category Past Two Years', 'chart_type': 'grouped_column_chart'}, {'question': 'What is the quarterly total revenue generation trend for all products in the past year?', 'chart_title': 'Quarterly Total Revenue Generation Trend for All Products Past Year', 'chart_type': 'line_chart'}], 'overall_title': {'overarching_title': 'Revenue Growth and Performance Analysis by Product Category'}}, {'main_question': 'How does the revenue generation trend correlate with the cost efficiency and product profitability of each product?', 'main_title': 'Revenue Generation vs Cost Efficiency and Product Profitability', 'main_chart_type': 'area_chart', 'sub_questions': [{'question': 'What is the monthly total revenue generation trend for each product in the past year?', 'chart_title': 'Monthly Total Revenue Generation Trend by Product (Past Year)', 'chart_type': 'grouped_column_chart', 'chart_axis': {'xAxis_title': 'Month', 'xAxis_column': 'Date', 'yAxis_title': 'Total Revenue Generation', 'yAxis_column': 'Revenue_Generation', 'yAxis_aggregation': 'SUM', 'yAxis2_title': '', 'yAxis2_column': '', 'yAxis2_aggregation': '', 'yAxis3_title': '', 'yAxis3_column': '', 'yAxis3_aggregation': '', 'series_title': 'Product', 'series_column': 'Product'}, 'chart_sql': \"SELECT CONCAT(YEAR(STR_TO_DATE(Date, '%d/%m/%Y')), '-', MONTH(STR_TO_DATE(Date, '%d/%m/%Y'))) AS xAxis, SUM(Revenue_Generation) AS yAxis, Product AS series FROM starhub_data_asset.data_asset_001_pcc WHERE STR_TO_DATE(Date, '%d/%m/%Y') BETWEEN DATE_SUB(CURDATE(), INTERVAL 1 YEAR) AND CURDATE() GROUP BY xAxis, series ORDER BY xAxis;\", 'chart_data':       xAxis         series      yAxis\n0   2023-10      BroadBand  2743715.0\n1   2023-10  Entertainment  2585464.0\n2   2023-10         Mobile  2911653.0\n3   2023-11      BroadBand  3278994.0\n4   2023-11  Entertainment  3089869.0\n5   2023-11         Mobile  3479695.0\n6   2023-12      BroadBand  3918701.0\n7   2023-12  Entertainment  3692680.0\n8   2023-12         Mobile  4158557.0\n9    2023-9      BroadBand  2295818.0\n10   2023-9  Entertainment  2163401.0\n11   2023-9         Mobile  2436341.0, 'chart_json': {'Subscription_ID': '', 'Subscription_Name': '', 'Client_ID': 'starhub_001', 'User_ID': 'goldius.leo@userdata.tech', 'Shared_User_ID': '', 'Chart_Name': 'Visual 3', 'Chart_Axis': {'xAxis_title': 'Month', 'xAxis_column': 'Date', 'yAxis_title': 'Total Revenue Generation', 'yAxis_column': 'Revenue_Generation', 'yAxis_aggregation': 'SUM', 'yAxis2_title': '', 'yAxis2_column': '', 'yAxis2_aggregation': '', 'yAxis3_title': '', 'yAxis3_column': '', 'yAxis3_aggregation': '', 'series_title': 'Product', 'series_column': 'Product'}, 'Chart_Query': \"SELECT CONCAT(YEAR(STR_TO_DATE(Date, '%d/%m/%Y')), '-', MONTH(STR_TO_DATE(Date, '%d/%m/%Y'))) AS xAxis, SUM(Revenue_Generation) AS yAxis, Product AS series FROM starhub_data_asset.data_asset_001_pcc WHERE STR_TO_DATE(Date, '%d/%m/%Y') BETWEEN DATE_SUB(CURDATE(), INTERVAL 1 YEAR) AND CURDATE() GROUP BY xAxis, series ORDER BY xAxis;\", 'Chart_SQL_Library': 'MySQL', 'Chart_Position': '2', 'Chart_Type': 'grouped_column_chart', 'Chart_Title': 'Monthly Total Revenue Generation Trend by Product (Past Year)', 'xAxis': 'Month', 'xAxis_Description': 'Month', 'X': ['2023-9', '2023-10', '2023-11', '2023-12'], 'yAxis': 'Total Revenue Generation', 'yAxis_Description': 'Total Revenue Generation', 'Y': [2295818.0, 2743715.0, 3278994.0, 3918701.0], 'Y2': [2163401.0, 2585464.0, 3089869.0, 3692680.0], 'Y3': [2436341.0, 2911653.0, 3479695.0, 4158557.0], 'yName': 'Total Revenue Generation (BroadBand)', 'y2Name': 'Total Revenue Generation (Entertainment)', 'y3Name': 'Total Revenue Generation (Mobile)', 'Smart_Insight': 'No Description', 'Business_Insight': 'No Description', 'Aggregated_Table_JSON': {'Subscription_ID': '', 'Subscription_Name': '', 'Client_ID': 'starhub_001', 'User_ID': 'goldius.leo@userdata.tech', 'Shared_User_ID': '', 'Chart_Name': 'Visual 3', 'Chart_Axis': {}, 'Chart_Query': \"SELECT CONCAT(YEAR(STR_TO_DATE(Date, '%d/%m/%Y')), '-', MONTH(STR_TO_DATE(Date, '%d/%m/%Y'))) AS xAxis, SUM(Revenue_Generation) AS yAxis, Product AS series FROM starhub_data_asset.data_asset_001_pcc WHERE STR_TO_DATE(Date, '%d/%m/%Y') BETWEEN DATE_SUB(CURDATE(), INTERVAL 1 YEAR) AND CURDATE() GROUP BY xAxis, series ORDER BY xAxis;\", 'Chart_SQL_Library': 'MySQL', 'Chart_Position': '2', 'Chart_Type': 'aggregated_table_chart', 'Chart_Size': 184, 'data': [{'Month': '2023-9', 'Product': 'BroadBand', 'Total Revenue Generation': 2295818.0}, {'Month': '2023-9', 'Product': 'Entertainment', 'Total Revenue Generation': 2163401.0}, {'Month': '2023-9', 'Product': 'Mobile', 'Total Revenue Generation': 2436341.0}, {'Month': '2023-10', 'Product': 'BroadBand', 'Total Revenue Generation': 2743715.0}, {'Month': '2023-10', 'Product': 'Entertainment', 'Total Revenue Generation': 2585464.0}, {'Month': '2023-10', 'Product': 'Mobile', 'Total Revenue Generation': 2911653.0}, {'Month': '2023-11', 'Product': 'BroadBand', 'Total Revenue Generation': 3278994.0}, {'Month': '2023-11', 'Product': 'Entertainment', 'Total Revenue Generation': 3089869.0}, {'Month': '2023-11', 'Product': 'Mobile', 'Total Revenue Generation': 3479695.0}, {'Month': '2023-12', 'Product': 'BroadBand', 'Total Revenue Generation': 3918701.0}, {'Month': '2023-12', 'Product': 'Entertainment', 'Total Revenue Generation': 3692680.0}, {'Month': '2023-12', 'Product': 'Mobile', 'Total Revenue Generation': 4158557.0}], 'Smart_Insight': 'No Description', 'Business_Insight': 'No Description', 'Database_Properties': {'database_type': 'mysql', 'database_name': 'datalake', 'username': 'AdaDB', 'password': 'Admin@2024', 'hostname': '20.184.17.187', 'port': 3306, 'db_tag': 'label1'}}, 'Aggregated_Table_Column': ['Revenue_Generation', 'Product', 'Date'], 'Database_Properties': {'database_type': 'mysql', 'database_name': 'datalake', 'username': 'AdaDB', 'password': 'Admin@2024', 'hostname': '20.184.17.187', 'port': 3306, 'db_tag': 'label1'}}}, {'question': 'How does the monthly average cost efficiency of each product change over the past year?', 'chart_title': 'Monthly Average Cost Efficiency Trend by Product (Past Year)', 'chart_type': 'line_chart', 'chart_axis': {'xAxis_title': 'Month', 'xAxis_column': 'Date', 'yAxis_title': 'Average Cost Efficiency', 'yAxis_column': 'Cost_Efficiency', 'yAxis_aggregation': 'AVG', 'yAxis2_title': '', 'yAxis2_column': '', 'yAxis2_aggregation': '', 'yAxis3_title': '', 'yAxis3_column': '', 'yAxis3_aggregation': '', 'series_title': 'Product', 'series_column': 'Product'}, 'chart_sql': \"SELECT CONCAT(YEAR(STR_TO_DATE(Date, '%d/%m/%Y')), '-', MONTH(STR_TO_DATE(Date, '%d/%m/%Y'))) AS xAxis, AVG(Cost_Efficiency) AS yAxis, Product AS series FROM starhub_data_asset.data_asset_001_pcc WHERE STR_TO_DATE(Date, '%d/%m/%Y') BETWEEN DATE_SUB(CURDATE(), INTERVAL 1 YEAR) AND CURDATE() GROUP BY xAxis, series ORDER BY xAxis;\", 'chart_data':       xAxis         series      yAxis\n0   2023-10      BroadBand   9.849748\n1   2023-10  Entertainment  10.145220\n2   2023-10         Mobile   9.562884\n3   2023-11      BroadBand   9.013954\n4   2023-11  Entertainment   9.284374\n5   2023-11         Mobile   8.751428\n6   2023-12      BroadBand   8.249086\n7   2023-12  Entertainment   8.496539\n8   2023-12         Mobile   8.008836\n9    2023-9      BroadBand  10.763005\n10   2023-9  Entertainment  11.085878\n11   2023-9         Mobile  10.449564, 'chart_json': {'Subscription_ID': '', 'Subscription_Name': '', 'Client_ID': 'starhub_001', 'User_ID': 'goldius.leo@userdata.tech', 'Shared_User_ID': '', 'Chart_Name': 'Visual 3', 'Chart_Axis': {'xAxis_title': 'Month', 'xAxis_column': 'Date', 'yAxis_title': 'Average Cost Efficiency', 'yAxis_column': 'Cost_Efficiency', 'yAxis_aggregation': 'AVG', 'yAxis2_title': '', 'yAxis2_column': '', 'yAxis2_aggregation': '', 'yAxis3_title': '', 'yAxis3_column': '', 'yAxis3_aggregation': '', 'series_title': 'Product', 'series_column': 'Product'}, 'Chart_Query': \"SELECT CONCAT(YEAR(STR_TO_DATE(Date, '%d/%m/%Y')), '-', MONTH(STR_TO_DATE(Date, '%d/%m/%Y'))) AS xAxis, AVG(Cost_Efficiency) AS yAxis, Product AS series FROM starhub_data_asset.data_asset_001_pcc WHERE STR_TO_DATE(Date, '%d/%m/%Y') BETWEEN DATE_SUB(CURDATE(), INTERVAL 1 YEAR) AND CURDATE() GROUP BY xAxis, series ORDER BY xAxis;\", 'Chart_SQL_Library': 'MySQL', 'Chart_Position': '3', 'Chart_Type': 'line_chart', 'Chart_Title': 'Monthly Average Cost Efficiency Trend by Product (Past Year)', 'xAxis': 'Month', 'xAxis_Description': 'Month', 'X': ['2023-9', '2023-10', '2023-11', '2023-12'], 'yAxis': 'Average Cost Efficiency', 'yAxis_Description': 'Average Cost Efficiency', 'Y': [10.763005, 9.849748, 9.013954, 8.249086], 'Y2': [11.085878, 10.14522, 9.284374, 8.496539], 'Y3': [10.449564, 9.562884, 8.751428, 8.008836], 'yName': 'Average Cost Efficiency (BroadBand)', 'y2Name': 'Average Cost Efficiency (Entertainment)', 'y3Name': 'Average Cost Efficiency (Mobile)', 'Smart_Insight': 'No Description', 'Business_Insight': 'No Description', 'Aggregated_Table_JSON': {'Subscription_ID': '', 'Subscription_Name': '', 'Client_ID': 'starhub_001', 'User_ID': 'goldius.leo@userdata.tech', 'Shared_User_ID': '', 'Chart_Name': 'Visual 3', 'Chart_Axis': {}, 'Chart_Query': \"SELECT CONCAT(YEAR(STR_TO_DATE(Date, '%d/%m/%Y')), '-', MONTH(STR_TO_DATE(Date, '%d/%m/%Y'))) AS xAxis, AVG(Cost_Efficiency) AS yAxis, Product AS series FROM starhub_data_asset.data_asset_001_pcc WHERE STR_TO_DATE(Date, '%d/%m/%Y') BETWEEN DATE_SUB(CURDATE(), INTERVAL 1 YEAR) AND CURDATE() GROUP BY xAxis, series ORDER BY xAxis;\", 'Chart_SQL_Library': 'MySQL', 'Chart_Position': '3', 'Chart_Type': 'aggregated_table_chart', 'Chart_Size': 184, 'data': [{'Month': '2023-9', 'Product': 'BroadBand', 'Average Cost Efficiency': 10.763005}, {'Month': '2023-9', 'Product': 'Entertainment', 'Average Cost Efficiency': 11.085878}, {'Month': '2023-9', 'Product': 'Mobile', 'Average Cost Efficiency': 10.449564}, {'Month': '2023-10', 'Product': 'BroadBand', 'Average Cost Efficiency': 9.849748}, {'Month': '2023-10', 'Product': 'Entertainment', 'Average Cost Efficiency': 10.14522}, {'Month': '2023-10', 'Product': 'Mobile', 'Average Cost Efficiency': 9.562884}, {'Month': '2023-11', 'Product': 'BroadBand', 'Average Cost Efficiency': 9.013954}, {'Month': '2023-11', 'Product': 'Entertainment', 'Average Cost Efficiency': 9.284374}, {'Month': '2023-11', 'Product': 'Mobile', 'Average Cost Efficiency': 8.751428}, {'Month': '2023-12', 'Product': 'BroadBand', 'Average Cost Efficiency': 8.249086}, {'Month': '2023-12', 'Product': 'Entertainment', 'Average Cost Efficiency': 8.496539}, {'Month': '2023-12', 'Product': 'Mobile', 'Average Cost Efficiency': 8.008836}], 'Smart_Insight': 'No Description', 'Business_Insight': 'No Description', 'Database_Properties': {'database_type': 'mysql', 'database_name': 'datalake', 'username': 'AdaDB', 'password': 'Admin@2024', 'hostname': '20.184.17.187', 'port': 3306, 'db_tag': 'label1'}}, 'Aggregated_Table_Column': ['Product', 'Cost_Efficiency', 'Date'], 'Database_Properties': {'database_type': 'mysql', 'database_name': 'datalake', 'username': 'AdaDB', 'password': 'Admin@2024', 'hostname': '20.184.17.187', 'port': 3306, 'db_tag': 'label1'}}}, {'question': 'What is the product-wise correlation between monthly total revenue generation and monthly average product profitability over the past year?', 'chart_title': 'Monthly Total Revenue Generation vs Monthly Average Product Profitability by Product (Past Year)', 'chart_type': 'radar_chart', 'chart_axis': {'xAxis_title': 'Product', 'xAxis_column': 'Product', 'yAxis_title': 'Monthly Total Revenue Generation', 'yAxis_column': 'Revenue_Generation', 'yAxis_aggregation': 'SUM', 'yAxis2_title': 'Monthly Average Product Profitability', 'yAxis2_column': 'Product_Profitability', 'yAxis2_aggregation': 'AVG', 'yAxis3_title': '', 'yAxis3_column': '', 'yAxis3_aggregation': '', 'series_title': '', 'series_column': ''}, 'chart_sql': \"SELECT      `Product` AS xAxis,      SUM(`Revenue_Generation`) AS yAxis,      AVG(`Product_Profitability`) AS yAxis2  FROM      starhub_data_asset.data_asset_001_pcc  WHERE      STR_TO_DATE(`Date`, '%m/%d/%Y') BETWEEN DATE_SUB(CURDATE(), INTERVAL 1 YEAR) AND CURDATE()  GROUP BY      xAxis  ORDER BY      xAxis;\", 'chart_data': Empty DataFrame\nColumns: [xAxis, yAxis, yAxis2]\nIndex: []}], 'overall_title': {'overarching_title': 'Revenue, Cost, and Profitability Trends by Product'}, 'main_chart_axis': {'xAxis_title': 'Revenue Generation', 'xAxis_column': 'Revenue_Generation', 'yAxis_title': 'Cost Efficiency', 'yAxis_column': 'Cost_Efficiency', 'yAxis_aggregation': 'AVG', 'yAxis2_title': 'Product Profitability', 'yAxis2_column': 'Product_Profitability', 'yAxis2_aggregation': 'AVG', 'yAxis3_title': '', 'yAxis3_column': '', 'yAxis3_aggregation': '', 'series_title': 'Product', 'series_column': 'Product'}, 'main_chart_sql': \"SELECT      CONCAT(YEAR(STR_TO_DATE(`Date`, '%d/%m/%Y')), '-', MONTH(STR_TO_DATE(`Date`, '%d/%m/%Y'))) AS xAxis,      AVG(`Cost_Efficiency`) AS yAxis,      AVG(`Product_Profitability`) AS yAxis2,      `Product` AS series  FROM      starhub_data_asset.data_asset_001_pcc  GROUP BY      CONCAT(YEAR(STR_TO_DATE(`Date`, '%d/%m/%Y')), '-', MONTH(STR_TO_DATE(`Date`, '%d/%m/%Y'))), `Product`;\", 'chart_data':       xAxis         series      yAxis    yAxis2\n0    2022-1      BroadBand  63.404052  3.170818\n1    2022-1  Entertainment  65.306122  3.265306\n2    2022-1         Mobile  61.558201  2.903867\n3   2022-10      BroadBand  28.545309  0.631735\n4   2022-10  Entertainment  29.401529  0.689773\n..      ...            ...        ...       ...\n66   2023-8      BroadBand  11.760985  0.108639\n68   2023-8         Mobile  11.418454  0.105513\n70   2023-9  Entertainment  11.085878  0.096607\n69   2023-9      BroadBand  10.763005  0.093823\n71   2023-9         Mobile  10.449564  0.085908\n\n[72 rows x 4 columns], 'main_chart_json': {'Subscription_ID': '', 'Subscription_Name': '', 'Client_ID': 'starhub_001', 'User_ID': 'goldius.leo@userdata.tech', 'Shared_User_ID': '', 'Chart_Name': 'Visual 3', 'Visual_Title': {'overarching_title': 'Revenue, Cost, and Profitability Trends by Product'}, 'Chart_Axis': {'xAxis_title': 'Revenue Generation', 'xAxis_column': 'Revenue_Generation', 'yAxis_title': 'Cost Efficiency', 'yAxis_column': 'Cost_Efficiency', 'yAxis_aggregation': 'AVG', 'yAxis2_title': 'Product Profitability', 'yAxis2_column': 'Product_Profitability', 'yAxis2_aggregation': 'AVG', 'yAxis3_title': '', 'yAxis3_column': '', 'yAxis3_aggregation': '', 'series_title': 'Product', 'series_column': 'Product'}, 'Chart_Query': \"SELECT      CONCAT(YEAR(STR_TO_DATE(`Date`, '%d/%m/%Y')), '-', MONTH(STR_TO_DATE(`Date`, '%d/%m/%Y'))) AS xAxis,      AVG(`Cost_Efficiency`) AS yAxis,      AVG(`Product_Profitability`) AS yAxis2,      `Product` AS series  FROM      starhub_data_asset.data_asset_001_pcc  GROUP BY      CONCAT(YEAR(STR_TO_DATE(`Date`, '%d/%m/%Y')), '-', MONTH(STR_TO_DATE(`Date`, '%d/%m/%Y'))), `Product`;\", 'Chart_SQL_Library': 'MySQL', 'Chart_Position': '1', 'Chart_Type': 'area_chart', 'Chart_Title': 'Revenue Generation vs Cost Efficiency and Product Profitability', 'xAxis': 'Revenue Generation', 'xAxis_Description': 'Revenue Generation', 'X': ['2022-1', '2022-2', '2022-3', '2022-4', '2022-5', '2022-6', '2022-7', '2022-8', '2022-9', '2022-10', '2022-11', '2022-12', '2023-1', '2023-2', '2023-3', '2023-4', '2023-5', '2023-6', '2023-7', '2023-8', '2023-9', '2023-10', '2023-11', '2023-12'], 'yAxis': 'Amount', 'yAxis_Description': 'Amount', 'Y': [63.404052, 58.023944, 53.100662, 48.594812, 44.471344, 40.697851, 37.244682, 34.08405, 31.191999, 28.545309, 26.123097, 23.906503, 21.877991, 20.021506, 18.322623, 16.767951, 15.345151, 14.043076, 12.851436, 11.760985, 10.763005, 9.849748, 9.013954, 8.249086], 'Y2': [65.306122, 59.764478, 54.693644, 50.05213, 45.805687, 41.918309, 38.361446, 35.106722, 32.127751, 29.401529, 26.90671, 24.623593, 22.534266, 20.622175, 18.872323, 17.270965, 15.805493, 14.464351, 13.23699, 12.113773, 11.085878, 10.14522, 9.284374, 8.496539], 'Y3': [61.558201, 56.334765, 51.553539, 47.179731, 43.176553, 39.512479, 36.15989, 33.09156, 30.283425, 27.714047, 25.362368, 23.210163, 21.240892, 19.438494, 17.788997, 16.27961, 14.898217, 13.634052, 12.477174, 11.418454, 10.449564, 9.562884, 8.751428, 8.008836], 'yName': 'Average Cost Efficiency (BroadBand)', 'y2Name': 'Average Cost Efficiency (Entertainment)', 'y3Name': 'Average Cost Efficiency (Mobile)', 'Smart_Insight': 'No Description', 'Business_Insight': 'No Description', 'Aggregated_Table_JSON': {'Subscription_ID': '', 'Subscription_Name': '', 'Client_ID': 'starhub_001', 'User_ID': 'goldius.leo@userdata.tech', 'Shared_User_ID': '', 'Chart_Name': 'Visual 3', 'Chart_Axis': {}, 'Chart_Query': \"SELECT      CONCAT(YEAR(STR_TO_DATE(`Date`, '%d/%m/%Y')), '-', MONTH(STR_TO_DATE(`Date`, '%d/%m/%Y'))) AS xAxis,      AVG(`Cost_Efficiency`) AS yAxis,      AVG(`Product_Profitability`) AS yAxis2,      `Product` AS series  FROM      starhub_data_asset.data_asset_001_pcc  GROUP BY      CONCAT(YEAR(STR_TO_DATE(`Date`, '%d/%m/%Y')), '-', MONTH(STR_TO_DATE(`Date`, '%d/%m/%Y'))), `Product`;\", 'Chart_SQL_Library': 'MySQL', 'Chart_Position': '1', 'Chart_Type': 'aggregated_table_chart', 'Chart_Size': 664, 'data': [{'Revenue Generation': '2022-1', 'Product': 'BroadBand', 'Cost Efficiency': 63.404052, 'Product Profitability': 3.170818}, {'Revenue Generation': '2022-1', 'Product': 'Entertainment', 'Cost Efficiency': 65.306122, 'Product Profitability': 3.265306}, {'Revenue Generation': '2022-1', 'Product': 'Mobile', 'Cost Efficiency': 61.558201, 'Product Profitability': 2.903867}, {'Revenue Generation': '2022-2', 'Product': 'Mobile', 'Cost Efficiency': 56.334765, 'Product Profitability': 2.507461}, {'Revenue Generation': '2022-2', 'Product': 'Entertainment', 'Cost Efficiency': 59.764478, 'Product Profitability': 2.819711}, {'Revenue Generation': '2022-2', 'Product': 'BroadBand', 'Cost Efficiency': 58.023944, 'Product Profitability': 2.582389}, {'Revenue Generation': '2022-3', 'Product': 'Mobile', 'Cost Efficiency': 51.553539, 'Product Profitability': 2.042287}, {'Revenue Generation': '2022-3', 'Product': 'BroadBand', 'Cost Efficiency': 53.100662, 'Product Profitability': 2.229762}, {'Revenue Generation': '2022-3', 'Product': 'Entertainment', 'Cost Efficiency': 54.693644, 'Product Profitability': 2.296525}, {'Revenue Generation': '2022-4', 'Product': 'Mobile', 'Cost Efficiency': 47.179731, 'Product Profitability': 1.763252}, {'Revenue Generation': '2022-4', 'Product': 'Entertainment', 'Cost Efficiency': 50.05213, 'Product Profitability': 1.98284}, {'Revenue Generation': '2022-4', 'Product': 'BroadBand', 'Cost Efficiency': 48.594812, 'Product Profitability': 1.816199}, {'Revenue Generation': '2022-5', 'Product': 'Mobile', 'Cost Efficiency': 43.176553, 'Product Profitability': 1.436328}, {'Revenue Generation': '2022-5', 'Product': 'Entertainment', 'Cost Efficiency': 45.805687, 'Product Profitability': 1.615137}, {'Revenue Generation': '2022-5', 'Product': 'BroadBand', 'Cost Efficiency': 44.471344, 'Product Profitability': 1.568734}, {'Revenue Generation': '2022-6', 'Product': 'Entertainment', 'Cost Efficiency': 41.918309, 'Product Profitability': 1.395}, {'Revenue Generation': '2022-6', 'Product': 'Mobile', 'Cost Efficiency': 39.512479, 'Product Profitability': 1.240507}, {'Revenue Generation': '2022-6', 'Product': 'BroadBand', 'Cost Efficiency': 40.697851, 'Product Profitability': 1.27731}, {'Revenue Generation': '2022-7', 'Product': 'BroadBand', 'Cost Efficiency': 37.244682, 'Product Profitability': 1.10312}, {'Revenue Generation': '2022-7', 'Product': 'Entertainment', 'Cost Efficiency': 38.361446, 'Product Profitability': 1.135892}, {'Revenue Generation': '2022-7', 'Product': 'Mobile', 'Cost Efficiency': 36.15989, 'Product Profitability': 1.010136}, {'Revenue Generation': '2022-8', 'Product': 'BroadBand', 'Cost Efficiency': 34.08405, 'Product Profitability': 0.898298}, {'Revenue Generation': '2022-8', 'Product': 'Mobile', 'Cost Efficiency': 33.09156, 'Product Profitability': 0.872299}, {'Revenue Generation': '2022-8', 'Product': 'Entertainment', 'Cost Efficiency': 35.106722, 'Product Profitability': 0.980944}, {'Revenue Generation': '2022-9', 'Product': 'Mobile', 'Cost Efficiency': 30.283425, 'Product Profitability': 0.710391}, {'Revenue Generation': '2022-9', 'Product': 'Entertainment', 'Cost Efficiency': 32.127751, 'Product Profitability': 0.798839}, {'Revenue Generation': '2022-9', 'Product': 'BroadBand', 'Cost Efficiency': 31.191999, 'Product Profitability': 0.775687}, {'Revenue Generation': '2022-10', 'Product': 'Mobile', 'Cost Efficiency': 27.714047, 'Product Profitability': 0.613374}, {'Revenue Generation': '2022-10', 'Product': 'Entertainment', 'Cost Efficiency': 29.401529, 'Product Profitability': 0.689773}, {'Revenue Generation': '2022-10', 'Product': 'BroadBand', 'Cost Efficiency': 28.545309, 'Product Profitability': 0.631735}, {'Revenue Generation': '2022-11', 'Product': 'Mobile', 'Cost Efficiency': 25.362368, 'Product Profitability': 0.499583}, {'Revenue Generation': '2022-11', 'Product': 'Entertainment', 'Cost Efficiency': 26.90671, 'Product Profitability': 0.561787}, {'Revenue Generation': '2022-11', 'Product': 'BroadBand', 'Cost Efficiency': 26.123097, 'Product Profitability': 0.545434}, {'Revenue Generation': '2022-12', 'Product': 'Entertainment', 'Cost Efficiency': 24.623593, 'Product Profitability': 0.48502}, {'Revenue Generation': '2022-12', 'Product': 'BroadBand', 'Cost Efficiency': 23.906503, 'Product Profitability': 0.444265}, {'Revenue Generation': '2022-12', 'Product': 'Mobile', 'Cost Efficiency': 23.210163, 'Product Profitability': 0.4315}, {'Revenue Generation': '2023-1', 'Product': 'BroadBand', 'Cost Efficiency': 21.877991, 'Product Profitability': 0.383704}, {'Revenue Generation': '2023-1', 'Product': 'Entertainment', 'Cost Efficiency': 22.534266, 'Product Profitability': 0.395071}, {'Revenue Generation': '2023-1', 'Product': 'Mobile', 'Cost Efficiency': 21.240892, 'Product Profitability': 0.351325}, {'Revenue Generation': '2023-2', 'Product': 'Mobile', 'Cost Efficiency': 19.438494, 'Product Profitability': 0.303405}, {'Revenue Generation': '2023-2', 'Product': 'BroadBand', 'Cost Efficiency': 20.021506, 'Product Profitability': 0.312421}, {'Revenue Generation': '2023-2', 'Product': 'Entertainment', 'Cost Efficiency': 20.622175, 'Product Profitability': 0.3412}, {'Revenue Generation': '2023-3', 'Product': 'Mobile', 'Cost Efficiency': 17.788997, 'Product Profitability': 0.247059}, {'Revenue Generation': '2023-3', 'Product': 'Entertainment', 'Cost Efficiency': 18.872323, 'Product Profitability': 0.277825}, {'Revenue Generation': '2023-3', 'Product': 'BroadBand', 'Cost Efficiency': 18.322623, 'Product Profitability': 0.269796}, {'Revenue Generation': '2023-4', 'Product': 'Entertainment', 'Cost Efficiency': 17.270965, 'Product Profitability': 0.239909}, {'Revenue Generation': '2023-4', 'Product': 'BroadBand', 'Cost Efficiency': 16.767951, 'Product Profitability': 0.2197}, {'Revenue Generation': '2023-4', 'Product': 'Mobile', 'Cost Efficiency': 16.27961, 'Product Profitability': 0.213332}, {'Revenue Generation': '2023-5', 'Product': 'Mobile', 'Cost Efficiency': 14.898217, 'Product Profitability': 0.173735}, {'Revenue Generation': '2023-5', 'Product': 'BroadBand', 'Cost Efficiency': 15.345151, 'Product Profitability': 0.1897}, {'Revenue Generation': '2023-5', 'Product': 'Entertainment', 'Cost Efficiency': 15.805493, 'Product Profitability': 0.195371}, {'Revenue Generation': '2023-6', 'Product': 'Mobile', 'Cost Efficiency': 13.634052, 'Product Profitability': 0.149997}, {'Revenue Generation': '2023-6', 'Product': 'Entertainment', 'Cost Efficiency': 14.464351, 'Product Profitability': 0.168685}, {'Revenue Generation': '2023-6', 'Product': 'BroadBand', 'Cost Efficiency': 14.043076, 'Product Profitability': 0.154494}, {'Revenue Generation': '2023-7', 'Product': 'Entertainment', 'Cost Efficiency': 13.23699, 'Product Profitability': 0.137385}, {'Revenue Generation': '2023-7', 'Product': 'BroadBand', 'Cost Efficiency': 12.851436, 'Product Profitability': 0.13338}, {'Revenue Generation': '2023-7', 'Product': 'Mobile', 'Cost Efficiency': 12.477174, 'Product Profitability': 0.122169}, {'Revenue Generation': '2023-8', 'Product': 'Entertainment', 'Cost Efficiency': 12.113773, 'Product Profitability': 0.118658}, {'Revenue Generation': '2023-8', 'Product': 'BroadBand', 'Cost Efficiency': 11.760985, 'Product Profitability': 0.108639}, {'Revenue Generation': '2023-8', 'Product': 'Mobile', 'Cost Efficiency': 11.418454, 'Product Profitability': 0.105513}, {'Revenue Generation': '2023-9', 'Product': 'Entertainment', 'Cost Efficiency': 11.085878, 'Product Profitability': 0.096607}, {'Revenue Generation': '2023-9', 'Product': 'Mobile', 'Cost Efficiency': 10.449564, 'Product Profitability': 0.085908}, {'Revenue Generation': '2023-9', 'Product': 'BroadBand', 'Cost Efficiency': 10.763005, 'Product Profitability': 0.093823}, {'Revenue Generation': '2023-10', 'Product': 'BroadBand', 'Cost Efficiency': 9.849748, 'Product Profitability': 0.076393}, {'Revenue Generation': '2023-10', 'Product': 'Entertainment', 'Cost Efficiency': 10.14522, 'Product Profitability': 0.083428}, {'Revenue Generation': '2023-10', 'Product': 'Mobile', 'Cost Efficiency': 9.562884, 'Product Profitability': 0.074185}, {'Revenue Generation': '2023-11', 'Product': 'BroadBand', 'Cost Efficiency': 9.013954, 'Product Profitability': 0.065965}, {'Revenue Generation': '2023-11', 'Product': 'Entertainment', 'Cost Efficiency': 9.284374, 'Product Profitability': 0.067932}, {'Revenue Generation': '2023-11', 'Product': 'Mobile', 'Cost Efficiency': 8.751428, 'Product Profitability': 0.060408}, {'Revenue Generation': '2023-12', 'Product': 'Mobile', 'Cost Efficiency': 8.008836, 'Product Profitability': 0.052158}, {'Revenue Generation': '2023-12', 'Product': 'Entertainment', 'Cost Efficiency': 8.496539, 'Product Profitability': 0.058657}, {'Revenue Generation': '2023-12', 'Product': 'BroadBand', 'Cost Efficiency': 8.249086, 'Product Profitability': 0.053717}], 'Smart_Insight': 'No Description', 'Business_Insight': 'No Description', 'Database_Properties': {'database_type': 'mysql', 'database_name': 'datalake', 'username': 'AdaDB', 'password': 'Admin@2024', 'hostname': '20.184.17.187', 'port': 3306, 'db_tag': 'label1'}}, 'Aggregated_Table_Column': ['Revenue_Generation', 'Cost_Efficiency', 'Product_Profitability', 'Product'], 'Database_Properties': {'database_type': 'mysql', 'database_name': 'datalake', 'username': 'AdaDB', 'password': 'Admin@2024', 'hostname': '20.184.17.187', 'port': 3306, 'db_tag': 'label1'}, 'Y4': [3.170818, 2.582389, 2.229762, 1.816199, 1.568734, 1.27731, 1.10312, 0.898298, 0.775687, 0.631735, 0.545434, 0.444265, 0.383704, 0.312421, 0.269796, 0.2197, 0.1897, 0.154494, 0.13338, 0.108639, 0.093823, 0.076393, 0.065965, 0.053717], 'y4Name': 'Average Product Profitability (BroadBand)', 'Y5': [3.265306, 2.819711, 2.296525, 1.98284, 1.615137, 1.395, 1.135892, 0.980944, 0.798839, 0.689773, 0.561787, 0.48502, 0.395071, 0.3412, 0.277825, 0.239909, 0.195371, 0.168685, 0.137385, 0.118658, 0.096607, 0.083428, 0.067932, 0.058657], 'y5Name': 'Average Product Profitability (Entertainment)', 'Y6': [2.903867, 2.507461, 2.042287, 1.763252, 1.436328, 1.240507, 1.010136, 0.872299, 0.710391, 0.613374, 0.499583, 0.4315, 0.351325, 0.303405, 0.247059, 0.213332, 0.173735, 0.149997, 0.122169, 0.105513, 0.085908, 0.074185, 0.060408, 0.052158], 'y6Name': 'Average Product Profitability (Mobile)'}}])",
    "Story_Questions": [
        {
            "main_question": "What is the total revenue generated by all products over the past year?",
            "main_title": "Total Revenue Generation Over Past Year",
            "main_chart_type": "line_chart",
            "sub_questions": [
                {
                    "question": "What is the average month-over-month growth rate for all products revenue in the past year?",
                    "chart_title": "Average Month-over-Month Growth Rate for All Products Revenue (Past Year)",
                    "chart_type": "spline_chart",
                    "chart_axis": {
                        "xAxis_title": "Month",
                        "xAxis_column": "Date",
                        "yAxis_title": "Total Revenue Generation",
                        "yAxis_column": "Revenue_Generation",
                        "yAxis_aggregation": "SUM",
                        "yAxis2_title": "",
                        "yAxis2_column": "",
                        "yAxis2_aggregation": "",
                        "yAxis3_title": "",
                        "yAxis3_column": "",
                        "yAxis3_aggregation": "",
                        "series_title": "",
                        "series_column": ""
                    },
                    "chart_sql": "SELECT CONCAT(YEAR(STR_TO_DATE(Date, '%m/%d/%Y')), '-', MONTH(STR_TO_DATE(Date, '%m/%d/%Y'))) AS xAxis, AVG((SUM(Revenue_Generation) - LAG(SUM(Revenue_Generation), 1, 0) OVER (ORDER BY STR_TO_DATE(Date, '%m/%d/%Y'))) / LAG(SUM(Revenue_Generation), 1, 0) OVER (ORDER BY STR_TO_DATE(Date, '%m/%d/%Y'))) AS yAxis FROM starhub_data_asset.data_asset_001_pcc WHERE STR_TO_DATE(Date, '%m/%d/%Y') BETWEEN DATE_SUB(CURDATE(), INTERVAL 1 YEAR) AND CURDATE() GROUP BY xAxis ORDER BY xAxis;",
                    "chart_data": "Empty DataFrame\nColumns: []\nIndex: []"
                },
                {
                    "question": "What is the total revenue generated by all products in each quarter of the past year?",
                    "chart_title": "Total Revenue Generated by All Products (Quarterly, Past Year)",
                    "chart_type": "bar_chart",
                    "chart_axis": {
                        "xAxis_title": "Quarter",
                        "xAxis_column": "Date",
                        "yAxis_title": "Total Revenue",
                        "yAxis_column": "Revenue_Generation",
                        "yAxis_aggregation": "SUM"
                    },
                    "chart_sql": "SELECT CONCAT(YEAR(STR_TO_DATE(Date, '%d/%m/%Y')), '-Q', QUARTER(STR_TO_DATE(Date, '%d/%m/%Y'))) AS xAxis, SUM(Revenue_Generation) AS yAxis FROM data_asset_001_pcc WHERE STR_TO_DATE(Date, '%d/%m/%Y') BETWEEN DATE_SUB(CURDATE(), INTERVAL 1 YEAR) AND CURDATE() GROUP BY xAxis ORDER BY xAxis;",
                    "chart_data": "Empty DataFrame\nColumns: []\nIndex: []"
                },
                {
                    "question": "What is the monthly total revenue generated by all products over the past year?",
                    "chart_title": "Monthly Total Revenue Generated by All Products (Past Year)",
                    "chart_type": "line_chart",
                    "chart_axis": {
                        "xAxis_title": "Month",
                        "xAxis_column": "Date",
                        "yAxis_title": "Total Revenue",
                        "yAxis_column": "Revenue_Generation",
                        "yAxis_aggregation": "SUM",
                        "yAxis2_title": "",
                        "yAxis2_column": "",
                        "yAxis2_aggregation": "",
                        "yAxis3_title": "",
                        "yAxis3_column": "",
                        "yAxis3_aggregation": "",
                        "series_title": "",
                        "series_column": ""
                    },
                    "chart_sql": "SELECT CONCAT(YEAR(STR_TO_DATE(Date, '%m/%d/%Y')), '-', MONTH(STR_TO_DATE(Date, '%m/%d/%Y'))) AS xAxis, SUM(Revenue_Generation) AS yAxis FROM starhub_data_asset.data_asset_001_pcc WHERE STR_TO_DATE(Date, '%m/%d/%Y') BETWEEN DATE_SUB(CURDATE(), INTERVAL 1 YEAR) AND CURDATE() GROUP BY CONCAT(YEAR(STR_TO_DATE(Date, '%m/%d/%Y')), '-', MONTH(STR_TO_DATE(Date, '%m/%d/%Y'))) ORDER BY CONCAT(YEAR(STR_TO_DATE(Date, '%m/%d/%Y')), '-', MONTH(STR_TO_DATE(Date, '%m/%d/%Y')));",
                    "chart_data": "Empty DataFrame\nColumns: [xAxis, yAxis]\nIndex: []"
                }
            ],
            "overall_title": {
                "overarching_title": "Revenue Performance and Growth Trends"
            }
        },
        {
            "main_question": "How does the revenue generation trend vary by product category?",
            "main_title": "Monthly Revenue Generation by Product Category",
            "main_chart_type": "grouped_bar_chart",
            "sub_questions": [
                {
                    "question": "What is the monthly total revenue generation trend for each product in the past year?",
                    "chart_title": "Monthly Total Revenue Generation Trend by Product (Past Year)",
                    "chart_type": "grouped_column_chart",
                    "chart_axis": {
                        "xAxis_title": "Month",
                        "xAxis_column": "Date",
                        "yAxis_title": "Total Revenue Generation",
                        "yAxis_column": "Revenue_Generation",
                        "yAxis_aggregation": "SUM",
                        "yAxis2_title": "",
                        "yAxis2_column": "",
                        "yAxis2_aggregation": "",
                        "yAxis3_title": "",
                        "yAxis3_column": "",
                        "yAxis3_aggregation": "",
                        "series_title": "Product",
                        "series_column": "Product"
                    },
                    "chart_sql": "SELECT CONCAT(YEAR(STR_TO_DATE(Date, '%d/%m/%Y')), '-', MONTH(STR_TO_DATE(Date, '%d/%m/%Y'))) AS xAxis, SUM(Revenue_Generation) AS yAxis, Product AS series FROM starhub_data_asset.data_asset_001_pcc WHERE STR_TO_DATE(Date, '%d/%m/%Y') BETWEEN DATE_SUB(CURDATE(), INTERVAL 1 YEAR) AND CURDATE() GROUP BY xAxis, series ORDER BY xAxis;",
                    "chart_data": "      xAxis         series      yAxis\n0   2023-10      BroadBand  2743715.0\n1   2023-10  Entertainment  2585464.0\n2   2023-10         Mobile  2911653.0\n3   2023-11      BroadBand  3278994.0\n4   2023-11  Entertainment  3089869.0\n5   2023-11         Mobile  3479695.0\n6   2023-12      BroadBand  3918701.0\n7   2023-12  Entertainment  3692680.0\n8   2023-12         Mobile  4158557.0\n9    2023-9      BroadBand  2295818.0\n10   2023-9  Entertainment  2163401.0\n11   2023-9         Mobile  2436341.0",
                    "chart_json": {
                        "Subscription_ID": "",
                        "Subscription_Name": "",
                        "Client_ID": "starhub_001",
                        "User_ID": "goldius.leo@userdata.tech",
                        "Shared_User_ID": "",
                        "Chart_Name": "Visual 1",
                        "Visual_Title": {
                            "overarching_title": "Revenue Trends by Product Category Analysis"
                        },
                        "Chart_Axis": {
                            "xAxis_title": "Month",
                            "xAxis_column": "Date",
                            "yAxis_title": "Total Revenue Generation",
                            "yAxis_column": "Revenue_Generation",
                            "yAxis_aggregation": "SUM",
                            "yAxis2_title": "",
                            "yAxis2_column": "",
                            "yAxis2_aggregation": "",
                            "yAxis3_title": "",
                            "yAxis3_column": "",
                            "yAxis3_aggregation": "",
                            "series_title": "Product",
                            "series_column": "Product"
                        },
                        "Chart_Query": "SELECT CONCAT(YEAR(STR_TO_DATE(Date, '%d/%m/%Y')), '-', MONTH(STR_TO_DATE(Date, '%d/%m/%Y'))) AS xAxis, SUM(Revenue_Generation) AS yAxis, Product AS series FROM starhub_data_asset.data_asset_001_pcc WHERE STR_TO_DATE(Date, '%d/%m/%Y') BETWEEN DATE_SUB(CURDATE(), INTERVAL 1 YEAR) AND CURDATE() GROUP BY xAxis, series ORDER BY xAxis;",
                        "Chart_SQL_Library": "MySQL",
                        "Chart_Position": "1",
                        "Chart_Type": "grouped_column_chart",
                        "Chart_Title": "Monthly Total Revenue Generation Trend by Product (Past Year)",
                        "xAxis": "Month",
                        "xAxis_Description": "Month",
                        "X": [
                            "2023-9",
                            "2023-10",
                            "2023-11",
                            "2023-12"
                        ],
                        "yAxis": "Total Revenue Generation",
                        "yAxis_Description": "Total Revenue Generation",
                        "Y": [
                            2295818.0,
                            2743715.0,
                            3278994.0,
                            3918701.0
                        ],
                        "Y2": [
                            2163401.0,
                            2585464.0,
                            3089869.0,
                            3692680.0
                        ],
                        "Y3": [
                            2436341.0,
                            2911653.0,
                            3479695.0,
                            4158557.0
                        ],
                        "yName": "Total Revenue Generation (BroadBand)",
                        "y2Name": "Total Revenue Generation (Entertainment)",
                        "y3Name": "Total Revenue Generation (Mobile)",
                        "Smart_Insight": "No Description",
                        "Business_Insight": "No Description",
                        "Aggregated_Table_JSON": {
                            "Subscription_ID": "",
                            "Subscription_Name": "",
                            "Client_ID": "starhub_001",
                            "User_ID": "goldius.leo@userdata.tech",
                            "Shared_User_ID": "",
                            "Chart_Name": "Visual 1",
                            "Chart_Axis": {},
                            "Chart_Query": "SELECT CONCAT(YEAR(STR_TO_DATE(Date, '%d/%m/%Y')), '-', MONTH(STR_TO_DATE(Date, '%d/%m/%Y'))) AS xAxis, SUM(Revenue_Generation) AS yAxis, Product AS series FROM starhub_data_asset.data_asset_001_pcc WHERE STR_TO_DATE(Date, '%d/%m/%Y') BETWEEN DATE_SUB(CURDATE(), INTERVAL 1 YEAR) AND CURDATE() GROUP BY xAxis, series ORDER BY xAxis;",
                            "Chart_SQL_Library": "MySQL",
                            "Chart_Position": "1",
                            "Chart_Type": "aggregated_table_chart",
                            "Chart_Size": 184,
                            "data": [
                                {
                                    "Month": "2023-9",
                                    "Product": "BroadBand",
                                    "Total Revenue Generation": 2295818.0
                                },
                                {
                                    "Month": "2023-9",
                                    "Product": "Entertainment",
                                    "Total Revenue Generation": 2163401.0
                                },
                                {
                                    "Month": "2023-9",
                                    "Product": "Mobile",
                                    "Total Revenue Generation": 2436341.0
                                },
                                {
                                    "Month": "2023-10",
                                    "Product": "BroadBand",
                                    "Total Revenue Generation": 2743715.0
                                },
                                {
                                    "Month": "2023-10",
                                    "Product": "Entertainment",
                                    "Total Revenue Generation": 2585464.0
                                },
                                {
                                    "Month": "2023-10",
                                    "Product": "Mobile",
                                    "Total Revenue Generation": 2911653.0
                                },
                                {
                                    "Month": "2023-11",
                                    "Product": "BroadBand",
                                    "Total Revenue Generation": 3278994.0
                                },
                                {
                                    "Month": "2023-11",
                                    "Product": "Entertainment",
                                    "Total Revenue Generation": 3089869.0
                                },
                                {
                                    "Month": "2023-11",
                                    "Product": "Mobile",
                                    "Total Revenue Generation": 3479695.0
                                },
                                {
                                    "Month": "2023-12",
                                    "Product": "BroadBand",
                                    "Total Revenue Generation": 3918701.0
                                },
                                {
                                    "Month": "2023-12",
                                    "Product": "Entertainment",
                                    "Total Revenue Generation": 3692680.0
                                },
                                {
                                    "Month": "2023-12",
                                    "Product": "Mobile",
                                    "Total Revenue Generation": 4158557.0
                                }
                            ],
                            "Smart_Insight": "No Description",
                            "Business_Insight": "No Description",
                            "Database_Properties": {
                                "database_type": "mysql",
                                "database_name": "datalake",
                                "username": "AdaDB",
                                "password": "Admin@2024",
                                "hostname": "20.184.17.187",
                                "port": 3306,
                                "db_tag": "label1"
                            }
                        },
                        "Aggregated_Table_Column": [
                            "Revenue_Generation",
                            "Product",
                            "Date"
                        ],
                        "Database_Properties": {
                            "database_type": "mysql",
                            "database_name": "datalake",
                            "username": "AdaDB",
                            "password": "Admin@2024",
                            "hostname": "20.184.17.187",
                            "port": 3306,
                            "db_tag": "label1"
                        }
                    }
                },
                {
                    "question": "What is the average month-over-month growth rate for each product category over the past two years?",
                    "chart_title": "Average Month-over-Month Growth Rate by Product Category (Past Two Years)",
                    "chart_type": "spline_chart",
                    "chart_axis": {
                        "xAxis_title": "Month",
                        "xAxis_column": "Date",
                        "yAxis_title": "Total Revenue Generation",
                        "yAxis_column": "Revenue_Generation",
                        "yAxis_aggregation": "SUM",
                        "yAxis2_title": "",
                        "yAxis2_column": "",
                        "yAxis2_aggregation": "",
                        "yAxis3_title": "",
                        "yAxis3_column": "",
                        "yAxis3_aggregation": "",
                        "series_title": "Product",
                        "series_column": "Product"
                    },
                    "chart_sql": "SELECT CONCAT(YEAR(STR_TO_DATE(`Date`, '%m/%d/%Y')), '-', MONTH(STR_TO_DATE(`Date`, '%m/%d/%Y'))) AS xAxis, `Product` AS series, AVG((`Revenue_Generation` - LAG(`Revenue_Generation`) OVER (PARTITION BY `Product` ORDER BY STR_TO_DATE(`Date`, '%m/%d/%Y'))) / LAG(`Revenue_Generation`) OVER (PARTITION BY `Product` ORDER BY STR_TO_DATE(`Date`, '%m/%d/%Y'))) AS yAxis FROM data_asset_001_pcc WHERE STR_TO_DATE(`Date`, '%m/%d/%Y') BETWEEN DATE_SUB(CURDATE(), INTERVAL 2 YEAR) AND CURDATE() GROUP BY xAxis, series ORDER BY xAxis;",
                    "chart_data": "Empty DataFrame\nColumns: []\nIndex: []"
                },
                {
                    "question": "What is the total revenue generation for each product category in the past quarter?",
                    "chart_title": "Total Revenue Generation by Product Category (Past Quarter)",
                    "chart_type": "bar_chart",
                    "chart_axis": {
                        "xAxis_title": "Product Category",
                        "xAxis_column": "Product",
                        "yAxis_title": "Total Revenue Generation",
                        "yAxis_column": "Revenue_Generation",
                        "yAxis_aggregation": "SUM"
                    },
                    "chart_sql": "SELECT `Product` AS xAxis, SUM(`Revenue_Generation`) AS yAxis FROM starhub_data_asset.data_asset_001_pcc WHERE STR_TO_DATE(`Date`, '%m/%d/%Y') BETWEEN DATE_SUB(CURDATE(), INTERVAL 1 QUARTER) AND CURDATE() GROUP BY xAxis ORDER BY xAxis;",
                    "chart_data": "Empty DataFrame\nColumns: [xAxis, yAxis]\nIndex: []"
                }
            ],
            "overall_title": {
                "overarching_title": "Revenue Trends by Product Category Analysis"
            }
        },
        {
            "main_question": "What is the average cost efficiency of all products over the past year?",
            "main_title": "Average Cost Efficiency Over Past Year",
            "main_chart_type": "line_chart",
            "sub_questions": [
                {
                    "question": "What is the total revenue generation for all products over the past year?",
                    "chart_title": "Total Revenue Generation for All Products Past Year",
                    "chart_type": "bar_chart",
                    "chart_axis": {
                        "xAxis_title": "Product",
                        "xAxis_column": "Product",
                        "yAxis_title": "Total Revenue Generation",
                        "yAxis_column": "Revenue_Generation",
                        "yAxis_aggregation": "SUM"
                    },
                    "chart_sql": "SELECT `Product` AS xAxis, SUM(`Revenue_Generation`) AS yAxis FROM starhub_data_asset.data_asset_001_pcc WHERE STR_TO_DATE(`Date`, '%m/%d/%Y') BETWEEN DATE_SUB(CURDATE(), INTERVAL 1 YEAR) AND CURDATE() GROUP BY xAxis ORDER BY xAxis;",
                    "chart_data": "Empty DataFrame\nColumns: [xAxis, yAxis]\nIndex: []"
                },
                {
                    "question": "What is the monthly average revenue generation trend for all products over the past year?",
                    "chart_title": "Monthly Average Revenue Generation Trend for All Products Past Year",
                    "chart_type": "line_chart",
                    "chart_axis": {
                        "xAxis_title": "Month",
                        "xAxis_column": "Date",
                        "yAxis_title": "Average Revenue Generation",
                        "yAxis_column": "Revenue_Generation",
                        "yAxis_aggregation": "AVG",
                        "yAxis2_title": "",
                        "yAxis2_column": "",
                        "yAxis2_aggregation": "",
                        "yAxis3_title": "",
                        "yAxis3_column": "",
                        "yAxis3_aggregation": "",
                        "series_title": "",
                        "series_column": ""
                    },
                    "chart_sql": "SELECT CONCAT(YEAR(STR_TO_DATE(Date, '%d/%m/%Y')), '-', MONTH(STR_TO_DATE(Date, '%d/%m/%Y'))) AS xAxis, AVG(Revenue_Generation) AS yAxis FROM data_asset_001_pcc WHERE STR_TO_DATE(Date, '%d/%m/%Y') BETWEEN DATE_SUB(CURDATE(), INTERVAL 1 YEAR) AND CURDATE() GROUP BY CONCAT(YEAR(STR_TO_DATE(Date, '%d/%m/%Y')), '-', MONTH(STR_TO_DATE(Date, '%d/%m/%Y'))) ORDER BY CONCAT(YEAR(STR_TO_DATE(Date, '%d/%m/%Y')), '-', MONTH(STR_TO_DATE(Date, '%d/%m/%Y')));",
                    "chart_data": "Empty DataFrame\nColumns: []\nIndex: []"
                },
                {
                    "question": "What is the product-wise distribution of average revenue generation over the past year?",
                    "chart_title": "Product-wise Distribution of Average Revenue Generation Past Year",
                    "chart_type": "grouped_bar_chart",
                    "chart_axis": {
                        "xAxis_title": "Product",
                        "xAxis_column": "Product",
                        "yAxis_title": "Average Revenue Generation",
                        "yAxis_column": "Revenue_Generation",
                        "yAxis_aggregation": "AVG",
                        "yAxis2_title": "",
                        "yAxis2_column": "",
                        "yAxis2_aggregation": "",
                        "yAxis3_title": "",
                        "yAxis3_column": "",
                        "yAxis3_aggregation": "",
                        "series_title": "",
                        "series_column": ""
                    },
                    "chart_sql": "SELECT `Product` AS xAxis, AVG(`Revenue_Generation`) AS yAxis FROM starhub_data_asset.data_asset_001_pcc WHERE STR_TO_DATE(`Date`, '%m/%d/%Y') BETWEEN DATE_SUB(CURDATE(), INTERVAL 1 YEAR) AND CURDATE() GROUP BY xAxis ORDER BY xAxis;",
                    "chart_data": "Empty DataFrame\nColumns: [xAxis, yAxis]\nIndex: []"
                }
            ],
            "overall_title": {
                "overarching_title": "Revenue and Cost Efficiency Analysis Over Past Year"
            }
        },
        {
            "main_question": "How does the product profitability vary by product category?",
            "main_title": "Average Product Profitability by Product Category",
            "main_chart_type": "bar_chart",
            "sub_questions": [
                {
                    "question": "What is the monthly total revenue generation trend for each product in the past year?",
                    "chart_title": "Monthly Total Revenue Generation Trend by Product (Past Year)",
                    "chart_type": "grouped_column_chart",
                    "chart_axis": {
                        "xAxis_title": "Month",
                        "xAxis_column": "Date",
                        "yAxis_title": "Total Revenue Generation",
                        "yAxis_column": "Revenue_Generation",
                        "yAxis_aggregation": "SUM",
                        "yAxis2_title": "",
                        "yAxis2_column": "",
                        "yAxis2_aggregation": "",
                        "yAxis3_title": "",
                        "yAxis3_column": "",
                        "yAxis3_aggregation": "",
                        "series_title": "Product",
                        "series_column": "Product"
                    },
                    "chart_sql": "SELECT CONCAT(YEAR(STR_TO_DATE(Date, '%d/%m/%Y')), '-', MONTH(STR_TO_DATE(Date, '%d/%m/%Y'))) AS xAxis, SUM(Revenue_Generation) AS yAxis, Product AS series FROM starhub_data_asset.data_asset_001_pcc WHERE STR_TO_DATE(Date, '%d/%m/%Y') BETWEEN DATE_SUB(CURDATE(), INTERVAL 1 YEAR) AND CURDATE() GROUP BY xAxis, series ORDER BY xAxis;",
                    "chart_data": "      xAxis         series      yAxis\n0   2023-10      BroadBand  2743715.0\n1   2023-10  Entertainment  2585464.0\n2   2023-10         Mobile  2911653.0\n3   2023-11      BroadBand  3278994.0\n4   2023-11  Entertainment  3089869.0\n5   2023-11         Mobile  3479695.0\n6   2023-12      BroadBand  3918701.0\n7   2023-12  Entertainment  3692680.0\n8   2023-12         Mobile  4158557.0\n9    2023-9      BroadBand  2295818.0\n10   2023-9  Entertainment  2163401.0\n11   2023-9         Mobile  2436341.0",
                    "chart_json": {
                        "Subscription_ID": "",
                        "Subscription_Name": "",
                        "Client_ID": "starhub_001",
                        "User_ID": "goldius.leo@userdata.tech",
                        "Shared_User_ID": "",
                        "Chart_Name": "Visual 2",
                        "Chart_Axis": {
                            "xAxis_title": "Month",
                            "xAxis_column": "Date",
                            "yAxis_title": "Total Revenue Generation",
                            "yAxis_column": "Revenue_Generation",
                            "yAxis_aggregation": "SUM",
                            "yAxis2_title": "",
                            "yAxis2_column": "",
                            "yAxis2_aggregation": "",
                            "yAxis3_title": "",
                            "yAxis3_column": "",
                            "yAxis3_aggregation": "",
                            "series_title": "Product",
                            "series_column": "Product"
                        },
                        "Chart_Query": "SELECT CONCAT(YEAR(STR_TO_DATE(Date, '%d/%m/%Y')), '-', MONTH(STR_TO_DATE(Date, '%d/%m/%Y'))) AS xAxis, SUM(Revenue_Generation) AS yAxis, Product AS series FROM starhub_data_asset.data_asset_001_pcc WHERE STR_TO_DATE(Date, '%d/%m/%Y') BETWEEN DATE_SUB(CURDATE(), INTERVAL 1 YEAR) AND CURDATE() GROUP BY xAxis, series ORDER BY xAxis;",
                        "Chart_SQL_Library": "MySQL",
                        "Chart_Position": "2",
                        "Chart_Type": "grouped_column_chart",
                        "Chart_Title": "Monthly Total Revenue Generation Trend by Product (Past Year)",
                        "xAxis": "Month",
                        "xAxis_Description": "Month",
                        "X": [
                            "2023-9",
                            "2023-10",
                            "2023-11",
                            "2023-12"
                        ],
                        "yAxis": "Total Revenue Generation",
                        "yAxis_Description": "Total Revenue Generation",
                        "Y": [
                            2295818.0,
                            2743715.0,
                            3278994.0,
                            3918701.0
                        ],
                        "Y2": [
                            2163401.0,
                            2585464.0,
                            3089869.0,
                            3692680.0
                        ],
                        "Y3": [
                            2436341.0,
                            2911653.0,
                            3479695.0,
                            4158557.0
                        ],
                        "yName": "Total Revenue Generation (BroadBand)",
                        "y2Name": "Total Revenue Generation (Entertainment)",
                        "y3Name": "Total Revenue Generation (Mobile)",
                        "Smart_Insight": "No Description",
                        "Business_Insight": "No Description",
                        "Aggregated_Table_JSON": {
                            "Subscription_ID": "",
                            "Subscription_Name": "",
                            "Client_ID": "starhub_001",
                            "User_ID": "goldius.leo@userdata.tech",
                            "Shared_User_ID": "",
                            "Chart_Name": "Visual 2",
                            "Chart_Axis": {},
                            "Chart_Query": "SELECT CONCAT(YEAR(STR_TO_DATE(Date, '%d/%m/%Y')), '-', MONTH(STR_TO_DATE(Date, '%d/%m/%Y'))) AS xAxis, SUM(Revenue_Generation) AS yAxis, Product AS series FROM starhub_data_asset.data_asset_001_pcc WHERE STR_TO_DATE(Date, '%d/%m/%Y') BETWEEN DATE_SUB(CURDATE(), INTERVAL 1 YEAR) AND CURDATE() GROUP BY xAxis, series ORDER BY xAxis;",
                            "Chart_SQL_Library": "MySQL",
                            "Chart_Position": "2",
                            "Chart_Type": "aggregated_table_chart",
                            "Chart_Size": 184,
                            "data": [
                                {
                                    "Month": "2023-9",
                                    "Product": "BroadBand",
                                    "Total Revenue Generation": 2295818.0
                                },
                                {
                                    "Month": "2023-9",
                                    "Product": "Entertainment",
                                    "Total Revenue Generation": 2163401.0
                                },
                                {
                                    "Month": "2023-9",
                                    "Product": "Mobile",
                                    "Total Revenue Generation": 2436341.0
                                },
                                {
                                    "Month": "2023-10",
                                    "Product": "BroadBand",
                                    "Total Revenue Generation": 2743715.0
                                },
                                {
                                    "Month": "2023-10",
                                    "Product": "Entertainment",
                                    "Total Revenue Generation": 2585464.0
                                },
                                {
                                    "Month": "2023-10",
                                    "Product": "Mobile",
                                    "Total Revenue Generation": 2911653.0
                                },
                                {
                                    "Month": "2023-11",
                                    "Product": "BroadBand",
                                    "Total Revenue Generation": 3278994.0
                                },
                                {
                                    "Month": "2023-11",
                                    "Product": "Entertainment",
                                    "Total Revenue Generation": 3089869.0
                                },
                                {
                                    "Month": "2023-11",
                                    "Product": "Mobile",
                                    "Total Revenue Generation": 3479695.0
                                },
                                {
                                    "Month": "2023-12",
                                    "Product": "BroadBand",
                                    "Total Revenue Generation": 3918701.0
                                },
                                {
                                    "Month": "2023-12",
                                    "Product": "Entertainment",
                                    "Total Revenue Generation": 3692680.0
                                },
                                {
                                    "Month": "2023-12",
                                    "Product": "Mobile",
                                    "Total Revenue Generation": 4158557.0
                                }
                            ],
                            "Smart_Insight": "No Description",
                            "Business_Insight": "No Description",
                            "Database_Properties": {
                                "database_type": "mysql",
                                "database_name": "datalake",
                                "username": "AdaDB",
                                "password": "Admin@2024",
                                "hostname": "20.184.17.187",
                                "port": 3306,
                                "db_tag": "label1"
                            }
                        },
                        "Aggregated_Table_Column": [
                            "Revenue_Generation",
                            "Product",
                            "Date"
                        ],
                        "Database_Properties": {
                            "database_type": "mysql",
                            "database_name": "datalake",
                            "username": "AdaDB",
                            "password": "Admin@2024",
                            "hostname": "20.184.17.187",
                            "port": 3306,
                            "db_tag": "label1"
                        }
                    }
                },
                {
                    "question": "What is the average month-over-month growth rate for all products revenue in the past two years?",
                    "chart_title": "Average Month-over-Month Growth Rate for All Products Revenue (Past Two Years)",
                    "chart_type": "spline_chart",
                    "chart_axis": {
                        "xAxis_title": "Month",
                        "xAxis_column": "Date",
                        "yAxis_title": "Total Revenue Generation",
                        "yAxis_column": "Revenue_Generation",
                        "yAxis_aggregation": "SUM",
                        "yAxis2_title": "",
                        "yAxis2_column": "",
                        "yAxis2_aggregation": "",
                        "yAxis3_title": "",
                        "yAxis3_column": "",
                        "yAxis3_aggregation": "",
                        "series_title": "Product",
                        "series_column": "Product"
                    },
                    "chart_sql": "SELECT CONCAT(YEAR(STR_TO_DATE(`Date`, '%m/%d/%Y')), '-', MONTH(STR_TO_DATE(`Date`, '%m/%d/%Y'))) AS xAxis, AVG((`Revenue_Generation` - LAG(`Revenue_Generation`) OVER (PARTITION BY `Product` ORDER BY STR_TO_DATE(`Date`, '%m/%d/%Y'))) / LAG(`Revenue_Generation`) OVER (PARTITION BY `Product` ORDER BY STR_TO_DATE(`Date`, '%m/%d/%Y'))) AS yAxis, `Product` AS series FROM data_asset_001_pcc WHERE STR_TO_DATE(`Date`, '%m/%d/%Y') BETWEEN DATE_SUB(CURDATE(), INTERVAL 2 YEAR) AND CURDATE() GROUP BY xAxis, series ORDER BY xAxis;",
                    "chart_data": "Empty DataFrame\nColumns: []\nIndex: []"
                },
                {
                    "question": "What is the distribution of monthly revenue generation for all products over the past year?",
                    "chart_title": "Distribution of Monthly Revenue Generation for All Products (Past Year)",
                    "chart_type": "histogram_chart",
                    "chart_axis": {
                        "xAxis_title": "Monthly Revenue Generation",
                        "xAxis_column": "Revenue_Generation"
                    },
                    "chart_sql": "SELECT `Revenue_Generation` AS xAxis FROM data_asset_001_pcc WHERE STR_TO_DATE(`Date`, '%m/%d/%Y') BETWEEN DATE_SUB(CURDATE(), INTERVAL 1 YEAR) AND CURDATE() GROUP BY xAxis ORDER BY xAxis;",
                    "chart_data": "Empty DataFrame\nColumns: []\nIndex: []"
                }
            ],
            "overall_title": {
                "overarching_title": "Product Profitability and Revenue Trends Analysis"
            }
        },
        {
            "main_question": "How does the revenue generation trend correlate with the cost efficiency and product profitability of each product?",
            "main_title": "Revenue Generation vs Cost Efficiency and Product Profitability",
            "main_chart_type": "area_chart",
            "sub_questions": [
                {
                    "question": "What is the monthly total revenue generation trend for each product in the past year?",
                    "chart_title": "Monthly Total Revenue Generation Trend by Product (Past Year)",
                    "chart_type": "grouped_column_chart",
                    "chart_axis": {
                        "xAxis_title": "Month",
                        "xAxis_column": "Date",
                        "yAxis_title": "Total Revenue Generation",
                        "yAxis_column": "Revenue_Generation",
                        "yAxis_aggregation": "SUM",
                        "yAxis2_title": "",
                        "yAxis2_column": "",
                        "yAxis2_aggregation": "",
                        "yAxis3_title": "",
                        "yAxis3_column": "",
                        "yAxis3_aggregation": "",
                        "series_title": "Product",
                        "series_column": "Product"
                    },
                    "chart_sql": "SELECT CONCAT(YEAR(STR_TO_DATE(Date, '%d/%m/%Y')), '-', MONTH(STR_TO_DATE(Date, '%d/%m/%Y'))) AS xAxis, SUM(Revenue_Generation) AS yAxis, Product AS series FROM starhub_data_asset.data_asset_001_pcc WHERE STR_TO_DATE(Date, '%d/%m/%Y') BETWEEN DATE_SUB(CURDATE(), INTERVAL 1 YEAR) AND CURDATE() GROUP BY xAxis, series ORDER BY xAxis;",
                    "chart_data": "      xAxis         series      yAxis\n0   2023-10      BroadBand  2743715.0\n1   2023-10  Entertainment  2585464.0\n2   2023-10         Mobile  2911653.0\n3   2023-11      BroadBand  3278994.0\n4   2023-11  Entertainment  3089869.0\n5   2023-11         Mobile  3479695.0\n6   2023-12      BroadBand  3918701.0\n7   2023-12  Entertainment  3692680.0\n8   2023-12         Mobile  4158557.0\n9    2023-9      BroadBand  2295818.0\n10   2023-9  Entertainment  2163401.0\n11   2023-9         Mobile  2436341.0",
                    "chart_json": {
                        "Subscription_ID": "",
                        "Subscription_Name": "",
                        "Client_ID": "starhub_001",
                        "User_ID": "goldius.leo@userdata.tech",
                        "Shared_User_ID": "",
                        "Chart_Name": "Visual 3",
                        "Chart_Axis": {
                            "xAxis_title": "Month",
                            "xAxis_column": "Date",
                            "yAxis_title": "Total Revenue Generation",
                            "yAxis_column": "Revenue_Generation",
                            "yAxis_aggregation": "SUM",
                            "yAxis2_title": "",
                            "yAxis2_column": "",
                            "yAxis2_aggregation": "",
                            "yAxis3_title": "",
                            "yAxis3_column": "",
                            "yAxis3_aggregation": "",
                            "series_title": "Product",
                            "series_column": "Product"
                        },
                        "Chart_Query": "SELECT CONCAT(YEAR(STR_TO_DATE(Date, '%d/%m/%Y')), '-', MONTH(STR_TO_DATE(Date, '%d/%m/%Y'))) AS xAxis, SUM(Revenue_Generation) AS yAxis, Product AS series FROM starhub_data_asset.data_asset_001_pcc WHERE STR_TO_DATE(Date, '%d/%m/%Y') BETWEEN DATE_SUB(CURDATE(), INTERVAL 1 YEAR) AND CURDATE() GROUP BY xAxis, series ORDER BY xAxis;",
                        "Chart_SQL_Library": "MySQL",
                        "Chart_Position": "2",
                        "Chart_Type": "grouped_column_chart",
                        "Chart_Title": "Monthly Total Revenue Generation Trend by Product (Past Year)",
                        "xAxis": "Month",
                        "xAxis_Description": "Month",
                        "X": [
                            "2023-9",
                            "2023-10",
                            "2023-11",
                            "2023-12"
                        ],
                        "yAxis": "Total Revenue Generation",
                        "yAxis_Description": "Total Revenue Generation",
                        "Y": [
                            2295818.0,
                            2743715.0,
                            3278994.0,
                            3918701.0
                        ],
                        "Y2": [
                            2163401.0,
                            2585464.0,
                            3089869.0,
                            3692680.0
                        ],
                        "Y3": [
                            2436341.0,
                            2911653.0,
                            3479695.0,
                            4158557.0
                        ],
                        "yName": "Total Revenue Generation (BroadBand)",
                        "y2Name": "Total Revenue Generation (Entertainment)",
                        "y3Name": "Total Revenue Generation (Mobile)",
                        "Smart_Insight": "No Description",
                        "Business_Insight": "No Description",
                        "Aggregated_Table_JSON": {
                            "Subscription_ID": "",
                            "Subscription_Name": "",
                            "Client_ID": "starhub_001",
                            "User_ID": "goldius.leo@userdata.tech",
                            "Shared_User_ID": "",
                            "Chart_Name": "Visual 3",
                            "Chart_Axis": {},
                            "Chart_Query": "SELECT CONCAT(YEAR(STR_TO_DATE(Date, '%d/%m/%Y')), '-', MONTH(STR_TO_DATE(Date, '%d/%m/%Y'))) AS xAxis, SUM(Revenue_Generation) AS yAxis, Product AS series FROM starhub_data_asset.data_asset_001_pcc WHERE STR_TO_DATE(Date, '%d/%m/%Y') BETWEEN DATE_SUB(CURDATE(), INTERVAL 1 YEAR) AND CURDATE() GROUP BY xAxis, series ORDER BY xAxis;",
                            "Chart_SQL_Library": "MySQL",
                            "Chart_Position": "2",
                            "Chart_Type": "aggregated_table_chart",
                            "Chart_Size": 184,
                            "data": [
                                {
                                    "Month": "2023-9",
                                    "Product": "BroadBand",
                                    "Total Revenue Generation": 2295818.0
                                },
                                {
                                    "Month": "2023-9",
                                    "Product": "Entertainment",
                                    "Total Revenue Generation": 2163401.0
                                },
                                {
                                    "Month": "2023-9",
                                    "Product": "Mobile",
                                    "Total Revenue Generation": 2436341.0
                                },
                                {
                                    "Month": "2023-10",
                                    "Product": "BroadBand",
                                    "Total Revenue Generation": 2743715.0
                                },
                                {
                                    "Month": "2023-10",
                                    "Product": "Entertainment",
                                    "Total Revenue Generation": 2585464.0
                                },
                                {
                                    "Month": "2023-10",
                                    "Product": "Mobile",
                                    "Total Revenue Generation": 2911653.0
                                },
                                {
                                    "Month": "2023-11",
                                    "Product": "BroadBand",
                                    "Total Revenue Generation": 3278994.0
                                },
                                {
                                    "Month": "2023-11",
                                    "Product": "Entertainment",
                                    "Total Revenue Generation": 3089869.0
                                },
                                {
                                    "Month": "2023-11",
                                    "Product": "Mobile",
                                    "Total Revenue Generation": 3479695.0
                                },
                                {
                                    "Month": "2023-12",
                                    "Product": "BroadBand",
                                    "Total Revenue Generation": 3918701.0
                                },
                                {
                                    "Month": "2023-12",
                                    "Product": "Entertainment",
                                    "Total Revenue Generation": 3692680.0
                                },
                                {
                                    "Month": "2023-12",
                                    "Product": "Mobile",
                                    "Total Revenue Generation": 4158557.0
                                }
                            ],
                            "Smart_Insight": "No Description",
                            "Business_Insight": "No Description",
                            "Database_Properties": {
                                "database_type": "mysql",
                                "database_name": "datalake",
                                "username": "AdaDB",
                                "password": "Admin@2024",
                                "hostname": "20.184.17.187",
                                "port": 3306,
                                "db_tag": "label1"
                            }
                        },
                        "Aggregated_Table_Column": [
                            "Revenue_Generation",
                            "Product",
                            "Date"
                        ],
                        "Database_Properties": {
                            "database_type": "mysql",
                            "database_name": "datalake",
                            "username": "AdaDB",
                            "password": "Admin@2024",
                            "hostname": "20.184.17.187",
                            "port": 3306,
                            "db_tag": "label1"
                        }
                    }
                },
                {
                    "question": "How does the monthly average cost efficiency of each product change over the past year?",
                    "chart_title": "Monthly Average Cost Efficiency Trend by Product (Past Year)",
                    "chart_type": "line_chart",
                    "chart_axis": {
                        "xAxis_title": "Month",
                        "xAxis_column": "Date",
                        "yAxis_title": "Average Cost Efficiency",
                        "yAxis_column": "Cost_Efficiency",
                        "yAxis_aggregation": "AVG",
                        "yAxis2_title": "",
                        "yAxis2_column": "",
                        "yAxis2_aggregation": "",
                        "yAxis3_title": "",
                        "yAxis3_column": "",
                        "yAxis3_aggregation": "",
                        "series_title": "Product",
                        "series_column": "Product"
                    },
                    "chart_sql": "SELECT CONCAT(YEAR(STR_TO_DATE(Date, '%d/%m/%Y')), '-', MONTH(STR_TO_DATE(Date, '%d/%m/%Y'))) AS xAxis, AVG(Cost_Efficiency) AS yAxis, Product AS series FROM starhub_data_asset.data_asset_001_pcc WHERE STR_TO_DATE(Date, '%d/%m/%Y') BETWEEN DATE_SUB(CURDATE(), INTERVAL 1 YEAR) AND CURDATE() GROUP BY xAxis, series ORDER BY xAxis;",
                    "chart_data": "      xAxis         series      yAxis\n0   2023-10      BroadBand   9.849748\n1   2023-10  Entertainment  10.145220\n2   2023-10         Mobile   9.562884\n3   2023-11      BroadBand   9.013954\n4   2023-11  Entertainment   9.284374\n5   2023-11         Mobile   8.751428\n6   2023-12      BroadBand   8.249086\n7   2023-12  Entertainment   8.496539\n8   2023-12         Mobile   8.008836\n9    2023-9      BroadBand  10.763005\n10   2023-9  Entertainment  11.085878\n11   2023-9         Mobile  10.449564",
                    "chart_json": {
                        "Subscription_ID": "",
                        "Subscription_Name": "",
                        "Client_ID": "starhub_001",
                        "User_ID": "goldius.leo@userdata.tech",
                        "Shared_User_ID": "",
                        "Chart_Name": "Visual 3",
                        "Chart_Axis": {
                            "xAxis_title": "Month",
                            "xAxis_column": "Date",
                            "yAxis_title": "Average Cost Efficiency",
                            "yAxis_column": "Cost_Efficiency",
                            "yAxis_aggregation": "AVG",
                            "yAxis2_title": "",
                            "yAxis2_column": "",
                            "yAxis2_aggregation": "",
                            "yAxis3_title": "",
                            "yAxis3_column": "",
                            "yAxis3_aggregation": "",
                            "series_title": "Product",
                            "series_column": "Product"
                        },
                        "Chart_Query": "SELECT CONCAT(YEAR(STR_TO_DATE(Date, '%d/%m/%Y')), '-', MONTH(STR_TO_DATE(Date, '%d/%m/%Y'))) AS xAxis, AVG(Cost_Efficiency) AS yAxis, Product AS series FROM starhub_data_asset.data_asset_001_pcc WHERE STR_TO_DATE(Date, '%d/%m/%Y') BETWEEN DATE_SUB(CURDATE(), INTERVAL 1 YEAR) AND CURDATE() GROUP BY xAxis, series ORDER BY xAxis;",
                        "Chart_SQL_Library": "MySQL",
                        "Chart_Position": "3",
                        "Chart_Type": "line_chart",
                        "Chart_Title": "Monthly Average Cost Efficiency Trend by Product (Past Year)",
                        "xAxis": "Month",
                        "xAxis_Description": "Month",
                        "X": [
                            "2023-9",
                            "2023-10",
                            "2023-11",
                            "2023-12"
                        ],
                        "yAxis": "Average Cost Efficiency",
                        "yAxis_Description": "Average Cost Efficiency",
                        "Y": [
                            10.763005,
                            9.849748,
                            9.013954,
                            8.249086
                        ],
                        "Y2": [
                            11.085878,
                            10.14522,
                            9.284374,
                            8.496539
                        ],
                        "Y3": [
                            10.449564,
                            9.562884,
                            8.751428,
                            8.008836
                        ],
                        "yName": "Average Cost Efficiency (BroadBand)",
                        "y2Name": "Average Cost Efficiency (Entertainment)",
                        "y3Name": "Average Cost Efficiency (Mobile)",
                        "Smart_Insight": "No Description",
                        "Business_Insight": "No Description",
                        "Aggregated_Table_JSON": {
                            "Subscription_ID": "",
                            "Subscription_Name": "",
                            "Client_ID": "starhub_001",
                            "User_ID": "goldius.leo@userdata.tech",
                            "Shared_User_ID": "",
                            "Chart_Name": "Visual 3",
                            "Chart_Axis": {},
                            "Chart_Query": "SELECT CONCAT(YEAR(STR_TO_DATE(Date, '%d/%m/%Y')), '-', MONTH(STR_TO_DATE(Date, '%d/%m/%Y'))) AS xAxis, AVG(Cost_Efficiency) AS yAxis, Product AS series FROM starhub_data_asset.data_asset_001_pcc WHERE STR_TO_DATE(Date, '%d/%m/%Y') BETWEEN DATE_SUB(CURDATE(), INTERVAL 1 YEAR) AND CURDATE() GROUP BY xAxis, series ORDER BY xAxis;",
                            "Chart_SQL_Library": "MySQL",
                            "Chart_Position": "3",
                            "Chart_Type": "aggregated_table_chart",
                            "Chart_Size": 184,
                            "data": [
                                {
                                    "Month": "2023-9",
                                    "Product": "BroadBand",
                                    "Average Cost Efficiency": 10.763005
                                },
                                {
                                    "Month": "2023-9",
                                    "Product": "Entertainment",
                                    "Average Cost Efficiency": 11.085878
                                },
                                {
                                    "Month": "2023-9",
                                    "Product": "Mobile",
                                    "Average Cost Efficiency": 10.449564
                                },
                                {
                                    "Month": "2023-10",
                                    "Product": "BroadBand",
                                    "Average Cost Efficiency": 9.849748
                                },
                                {
                                    "Month": "2023-10",
                                    "Product": "Entertainment",
                                    "Average Cost Efficiency": 10.14522
                                },
                                {
                                    "Month": "2023-10",
                                    "Product": "Mobile",
                                    "Average Cost Efficiency": 9.562884
                                },
                                {
                                    "Month": "2023-11",
                                    "Product": "BroadBand",
                                    "Average Cost Efficiency": 9.013954
                                },
                                {
                                    "Month": "2023-11",
                                    "Product": "Entertainment",
                                    "Average Cost Efficiency": 9.284374
                                },
                                {
                                    "Month": "2023-11",
                                    "Product": "Mobile",
                                    "Average Cost Efficiency": 8.751428
                                },
                                {
                                    "Month": "2023-12",
                                    "Product": "BroadBand",
                                    "Average Cost Efficiency": 8.249086
                                },
                                {
                                    "Month": "2023-12",
                                    "Product": "Entertainment",
                                    "Average Cost Efficiency": 8.496539
                                },
                                {
                                    "Month": "2023-12",
                                    "Product": "Mobile",
                                    "Average Cost Efficiency": 8.008836
                                }
                            ],
                            "Smart_Insight": "No Description",
                            "Business_Insight": "No Description",
                            "Database_Properties": {
                                "database_type": "mysql",
                                "database_name": "datalake",
                                "username": "AdaDB",
                                "password": "Admin@2024",
                                "hostname": "20.184.17.187",
                                "port": 3306,
                                "db_tag": "label1"
                            }
                        },
                        "Aggregated_Table_Column": [
                            "Product",
                            "Cost_Efficiency",
                            "Date"
                        ],
                        "Database_Properties": {
                            "database_type": "mysql",
                            "database_name": "datalake",
                            "username": "AdaDB",
                            "password": "Admin@2024",
                            "hostname": "20.184.17.187",
                            "port": 3306,
                            "db_tag": "label1"
                        }
                    }
                },
                {
                    "question": "What is the product-wise correlation between monthly total revenue generation and monthly average product profitability over the past year?",
                    "chart_title": "Monthly Total Revenue Generation vs Monthly Average Product Profitability by Product (Past Year)",
                    "chart_type": "radar_chart",
                    "chart_axis": {
                        "xAxis_title": "Product",
                        "xAxis_column": "Product",
                        "yAxis_title": "Monthly Total Revenue Generation",
                        "yAxis_column": "Revenue_Generation",
                        "yAxis_aggregation": "SUM",
                        "yAxis2_title": "Monthly Average Product Profitability",
                        "yAxis2_column": "Product_Profitability",
                        "yAxis2_aggregation": "AVG",
                        "yAxis3_title": "",
                        "yAxis3_column": "",
                        "yAxis3_aggregation": "",
                        "series_title": "",
                        "series_column": ""
                    },
                    "chart_sql": "SELECT      `Product` AS xAxis,      SUM(`Revenue_Generation`) AS yAxis,      AVG(`Product_Profitability`) AS yAxis2  FROM      starhub_data_asset.data_asset_001_pcc  WHERE      STR_TO_DATE(`Date`, '%m/%d/%Y') BETWEEN DATE_SUB(CURDATE(), INTERVAL 1 YEAR) AND CURDATE()  GROUP BY      xAxis  ORDER BY      xAxis;",
                    "chart_data": "Empty DataFrame\nColumns: [xAxis, yAxis, yAxis2]\nIndex: []"
                }
            ],
            "overall_title": {
                "overarching_title": "Revenue, Cost, and Profitability Trends by Product"
            }
        }
    ],
    "JSON": [
        {
            "Subscription_ID": "",
            "Subscription_Name": "",
            "Client_ID": "starhub_001",
            "User_ID": "goldius.leo@userdata.tech",
            "Shared_User_ID": "",
            "Chart_Name": "Visual 1",
            "Visual_Title": {
                "overarching_title": "Revenue Trends by Product Category Analysis"
            },
            "Chart_Axis": {
                "xAxis_title": "Month",
                "xAxis_column": "Date",
                "yAxis_title": "Total Revenue Generation",
                "yAxis_column": "Revenue_Generation",
                "yAxis_aggregation": "SUM",
                "yAxis2_title": "",
                "yAxis2_column": "",
                "yAxis2_aggregation": "",
                "yAxis3_title": "",
                "yAxis3_column": "",
                "yAxis3_aggregation": "",
                "series_title": "Product",
                "series_column": "Product"
            },
            "Chart_Query": "SELECT CONCAT(YEAR(STR_TO_DATE(Date, '%d/%m/%Y')), '-', MONTH(STR_TO_DATE(Date, '%d/%m/%Y'))) AS xAxis, SUM(Revenue_Generation) AS yAxis, Product AS series FROM starhub_data_asset.data_asset_001_pcc WHERE STR_TO_DATE(Date, '%d/%m/%Y') BETWEEN DATE_SUB(CURDATE(), INTERVAL 1 YEAR) AND CURDATE() GROUP BY xAxis, series ORDER BY xAxis;",
            "Chart_SQL_Library": "MySQL",
            "Chart_Position": "1",
            "Chart_Type": "grouped_column_chart",
            "Chart_Title": "Monthly Total Revenue Generation Trend by Product (Past Year)",
            "xAxis": "Month",
            "xAxis_Description": "Month",
            "X": [
                "2023-9",
                "2023-10",
                "2023-11",
                "2023-12"
            ],
            "yAxis": "Total Revenue Generation",
            "yAxis_Description": "Total Revenue Generation",
            "Y": [
                2295818.0,
                2743715.0,
                3278994.0,
                3918701.0
            ],
            "Y2": [
                2163401.0,
                2585464.0,
                3089869.0,
                3692680.0
            ],
            "Y3": [
                2436341.0,
                2911653.0,
                3479695.0,
                4158557.0
            ],
            "yName": "Total Revenue Generation (BroadBand)",
            "y2Name": "Total Revenue Generation (Entertainment)",
            "y3Name": "Total Revenue Generation (Mobile)",
            "Smart_Insight": "No Description",
            "Business_Insight": "No Description",
            "Aggregated_Table_JSON": {
                "Subscription_ID": "",
                "Subscription_Name": "",
                "Client_ID": "starhub_001",
                "User_ID": "goldius.leo@userdata.tech",
                "Shared_User_ID": "",
                "Chart_Name": "Visual 1",
                "Chart_Axis": {},
                "Chart_Query": "SELECT CONCAT(YEAR(STR_TO_DATE(Date, '%d/%m/%Y')), '-', MONTH(STR_TO_DATE(Date, '%d/%m/%Y'))) AS xAxis, SUM(Revenue_Generation) AS yAxis, Product AS series FROM starhub_data_asset.data_asset_001_pcc WHERE STR_TO_DATE(Date, '%d/%m/%Y') BETWEEN DATE_SUB(CURDATE(), INTERVAL 1 YEAR) AND CURDATE() GROUP BY xAxis, series ORDER BY xAxis;",
                "Chart_SQL_Library": "MySQL",
                "Chart_Position": "1",
                "Chart_Type": "aggregated_table_chart",
                "Chart_Size": 184,
                "data": [
                    {
                        "Month": "2023-9",
                        "Product": "BroadBand",
                        "Total Revenue Generation": 2295818.0
                    },
                    {
                        "Month": "2023-9",
                        "Product": "Entertainment",
                        "Total Revenue Generation": 2163401.0
                    },
                    {
                        "Month": "2023-9",
                        "Product": "Mobile",
                        "Total Revenue Generation": 2436341.0
                    },
                    {
                        "Month": "2023-10",
                        "Product": "BroadBand",
                        "Total Revenue Generation": 2743715.0
                    },
                    {
                        "Month": "2023-10",
                        "Product": "Entertainment",
                        "Total Revenue Generation": 2585464.0
                    },
                    {
                        "Month": "2023-10",
                        "Product": "Mobile",
                        "Total Revenue Generation": 2911653.0
                    },
                    {
                        "Month": "2023-11",
                        "Product": "BroadBand",
                        "Total Revenue Generation": 3278994.0
                    },
                    {
                        "Month": "2023-11",
                        "Product": "Entertainment",
                        "Total Revenue Generation": 3089869.0
                    },
                    {
                        "Month": "2023-11",
                        "Product": "Mobile",
                        "Total Revenue Generation": 3479695.0
                    },
                    {
                        "Month": "2023-12",
                        "Product": "BroadBand",
                        "Total Revenue Generation": 3918701.0
                    },
                    {
                        "Month": "2023-12",
                        "Product": "Entertainment",
                        "Total Revenue Generation": 3692680.0
                    },
                    {
                        "Month": "2023-12",
                        "Product": "Mobile",
                        "Total Revenue Generation": 4158557.0
                    }
                ],
                "Smart_Insight": "No Description",
                "Business_Insight": "No Description",
                "Database_Properties": {
                    "database_type": "mysql",
                    "database_name": "datalake",
                    "username": "AdaDB",
                    "password": "Admin@2024",
                    "hostname": "20.184.17.187",
                    "port": 3306,
                    "db_tag": "label1"
                }
            },
            "Aggregated_Table_Column": [
                "Revenue_Generation",
                "Product",
                "Date"
            ],
            "Database_Properties": {
                "database_type": "mysql",
                "database_name": "datalake",
                "username": "AdaDB",
                "password": "Admin@2024",
                "hostname": "20.184.17.187",
                "port": 3306,
                "db_tag": "label1"
            }
        },
        {
            "Subscription_ID": "",
            "Subscription_Name": "",
            "Client_ID": "starhub_001",
            "User_ID": "goldius.leo@userdata.tech",
            "Shared_User_ID": "",
            "Chart_Name": "Visual 2",
            "Visual_Title": {
                "overarching_title": "Product Profitability and Revenue Trends Analysis"
            },
            "Chart_Axis": {
                "xAxis_title": "Product Category",
                "xAxis_column": "Product",
                "yAxis_title": "Average Product Profitability",
                "yAxis_column": "Product_Profitability",
                "yAxis_aggregation": "AVG"
            },
            "Chart_Query": "SELECT `Product` AS xAxis, AVG(`Product_Profitability`) AS yAxis FROM starhub_data_asset.data_asset_001_pcc GROUP BY `Product` ORDER BY xAxis;",
            "Chart_SQL_Library": "MySQL",
            "Chart_Position": "1",
            "Chart_Type": "bar_chart",
            "Chart_Title": "Average Product Profitability by Product Category",
            "xAxis": "Product Category",
            "xAxis_Description": "Product Category",
            "X": [
                "BroadBand",
                "Entertainment",
                "Mobile"
            ],
            "yAxis": "Average Product Profitability",
            "yAxis_Description": "Average Product Profitability",
            "Y": [
                0.7960617916666667,
                0.84197925,
                0.7487574583333333
            ],
            "Smart_Insight": "No Description",
            "Business_Insight": "No Description",
            "Aggregated_Table_JSON": {
                "Subscription_ID": "",
                "Subscription_Name": "",
                "Client_ID": "starhub_001",
                "User_ID": "goldius.leo@userdata.tech",
                "Shared_User_ID": "",
                "Chart_Name": "Visual 2",
                "Chart_Axis": {},
                "Chart_Query": "SELECT `Product` AS xAxis, AVG(`Product_Profitability`) AS yAxis FROM starhub_data_asset.data_asset_001_pcc GROUP BY `Product` ORDER BY xAxis;",
                "Chart_SQL_Library": "MySQL",
                "Chart_Position": "1",
                "Chart_Type": "aggregated_table_chart",
                "Chart_Size": 88,
                "data": [
                    {
                        "Product Category": "BroadBand",
                        "Average Product Profitability": 0.7960617916666667
                    },
                    {
                        "Product Category": "Entertainment",
                        "Average Product Profitability": 0.84197925
                    },
                    {
                        "Product Category": "Mobile",
                        "Average Product Profitability": 0.7487574583333333
                    }
                ],
                "Smart_Insight": "No Description",
                "Business_Insight": "No Description",
                "Database_Properties": {
                    "database_type": "mysql",
                    "database_name": "datalake",
                    "username": "AdaDB",
                    "password": "Admin@2024",
                    "hostname": "20.184.17.187",
                    "port": 3306,
                    "db_tag": "label1"
                }
            },
            "Aggregated_Table_Column": [
                "Product",
                "Product_Profitability"
            ],
            "Database_Properties": {
                "database_type": "mysql",
                "database_name": "datalake",
                "username": "AdaDB",
                "password": "Admin@2024",
                "hostname": "20.184.17.187",
                "port": 3306,
                "db_tag": "label1"
            },
            "yName": "Average Product Profitability"
        },
        {
            "Subscription_ID": "",
            "Subscription_Name": "",
            "Client_ID": "starhub_001",
            "User_ID": "goldius.leo@userdata.tech",
            "Shared_User_ID": "",
            "Chart_Name": "Visual 2",
            "Chart_Axis": {
                "xAxis_title": "Month",
                "xAxis_column": "Date",
                "yAxis_title": "Total Revenue Generation",
                "yAxis_column": "Revenue_Generation",
                "yAxis_aggregation": "SUM",
                "yAxis2_title": "",
                "yAxis2_column": "",
                "yAxis2_aggregation": "",
                "yAxis3_title": "",
                "yAxis3_column": "",
                "yAxis3_aggregation": "",
                "series_title": "Product",
                "series_column": "Product"
            },
            "Chart_Query": "SELECT CONCAT(YEAR(STR_TO_DATE(Date, '%d/%m/%Y')), '-', MONTH(STR_TO_DATE(Date, '%d/%m/%Y'))) AS xAxis, SUM(Revenue_Generation) AS yAxis, Product AS series FROM starhub_data_asset.data_asset_001_pcc WHERE STR_TO_DATE(Date, '%d/%m/%Y') BETWEEN DATE_SUB(CURDATE(), INTERVAL 1 YEAR) AND CURDATE() GROUP BY xAxis, series ORDER BY xAxis;",
            "Chart_SQL_Library": "MySQL",
            "Chart_Position": "2",
            "Chart_Type": "grouped_column_chart",
            "Chart_Title": "Monthly Total Revenue Generation Trend by Product (Past Year)",
            "xAxis": "Month",
            "xAxis_Description": "Month",
            "X": [
                "2023-9",
                "2023-10",
                "2023-11",
                "2023-12"
            ],
            "yAxis": "Total Revenue Generation",
            "yAxis_Description": "Total Revenue Generation",
            "Y": [
                2295818.0,
                2743715.0,
                3278994.0,
                3918701.0
            ],
            "Y2": [
                2163401.0,
                2585464.0,
                3089869.0,
                3692680.0
            ],
            "Y3": [
                2436341.0,
                2911653.0,
                3479695.0,
                4158557.0
            ],
            "yName": "Total Revenue Generation (BroadBand)",
            "y2Name": "Total Revenue Generation (Entertainment)",
            "y3Name": "Total Revenue Generation (Mobile)",
            "Smart_Insight": "No Description",
            "Business_Insight": "No Description",
            "Aggregated_Table_JSON": {
                "Subscription_ID": "",
                "Subscription_Name": "",
                "Client_ID": "starhub_001",
                "User_ID": "goldius.leo@userdata.tech",
                "Shared_User_ID": "",
                "Chart_Name": "Visual 2",
                "Chart_Axis": {},
                "Chart_Query": "SELECT CONCAT(YEAR(STR_TO_DATE(Date, '%d/%m/%Y')), '-', MONTH(STR_TO_DATE(Date, '%d/%m/%Y'))) AS xAxis, SUM(Revenue_Generation) AS yAxis, Product AS series FROM starhub_data_asset.data_asset_001_pcc WHERE STR_TO_DATE(Date, '%d/%m/%Y') BETWEEN DATE_SUB(CURDATE(), INTERVAL 1 YEAR) AND CURDATE() GROUP BY xAxis, series ORDER BY xAxis;",
                "Chart_SQL_Library": "MySQL",
                "Chart_Position": "2",
                "Chart_Type": "aggregated_table_chart",
                "Chart_Size": 184,
                "data": [
                    {
                        "Month": "2023-9",
                        "Product": "BroadBand",
                        "Total Revenue Generation": 2295818.0
                    },
                    {
                        "Month": "2023-9",
                        "Product": "Entertainment",
                        "Total Revenue Generation": 2163401.0
                    },
                    {
                        "Month": "2023-9",
                        "Product": "Mobile",
                        "Total Revenue Generation": 2436341.0
                    },
                    {
                        "Month": "2023-10",
                        "Product": "BroadBand",
                        "Total Revenue Generation": 2743715.0
                    },
                    {
                        "Month": "2023-10",
                        "Product": "Entertainment",
                        "Total Revenue Generation": 2585464.0
                    },
                    {
                        "Month": "2023-10",
                        "Product": "Mobile",
                        "Total Revenue Generation": 2911653.0
                    },
                    {
                        "Month": "2023-11",
                        "Product": "BroadBand",
                        "Total Revenue Generation": 3278994.0
                    },
                    {
                        "Month": "2023-11",
                        "Product": "Entertainment",
                        "Total Revenue Generation": 3089869.0
                    },
                    {
                        "Month": "2023-11",
                        "Product": "Mobile",
                        "Total Revenue Generation": 3479695.0
                    },
                    {
                        "Month": "2023-12",
                        "Product": "BroadBand",
                        "Total Revenue Generation": 3918701.0
                    },
                    {
                        "Month": "2023-12",
                        "Product": "Entertainment",
                        "Total Revenue Generation": 3692680.0
                    },
                    {
                        "Month": "2023-12",
                        "Product": "Mobile",
                        "Total Revenue Generation": 4158557.0
                    }
                ],
                "Smart_Insight": "No Description",
                "Business_Insight": "No Description",
                "Database_Properties": {
                    "database_type": "mysql",
                    "database_name": "datalake",
                    "username": "AdaDB",
                    "password": "Admin@2024",
                    "hostname": "20.184.17.187",
                    "port": 3306,
                    "db_tag": "label1"
                }
            },
            "Aggregated_Table_Column": [
                "Revenue_Generation",
                "Product",
                "Date"
            ],
            "Database_Properties": {
                "database_type": "mysql",
                "database_name": "datalake",
                "username": "AdaDB",
                "password": "Admin@2024",
                "hostname": "20.184.17.187",
                "port": 3306,
                "db_tag": "label1"
            }
        },
        {
            "Subscription_ID": "",
            "Subscription_Name": "",
            "Client_ID": "starhub_001",
            "User_ID": "goldius.leo@userdata.tech",
            "Shared_User_ID": "",
            "Chart_Name": "Visual 3",
            "Visual_Title": {
                "overarching_title": "Revenue, Cost, and Profitability Trends by Product"
            },
            "Chart_Axis": {
                "xAxis_title": "Revenue Generation",
                "xAxis_column": "Revenue_Generation",
                "yAxis_title": "Cost Efficiency",
                "yAxis_column": "Cost_Efficiency",
                "yAxis_aggregation": "AVG",
                "yAxis2_title": "Product Profitability",
                "yAxis2_column": "Product_Profitability",
                "yAxis2_aggregation": "AVG",
                "yAxis3_title": "",
                "yAxis3_column": "",
                "yAxis3_aggregation": "",
                "series_title": "Product",
                "series_column": "Product"
            },
            "Chart_Query": "SELECT      CONCAT(YEAR(STR_TO_DATE(`Date`, '%d/%m/%Y')), '-', MONTH(STR_TO_DATE(`Date`, '%d/%m/%Y'))) AS xAxis,      AVG(`Cost_Efficiency`) AS yAxis,      AVG(`Product_Profitability`) AS yAxis2,      `Product` AS series  FROM      starhub_data_asset.data_asset_001_pcc  GROUP BY      CONCAT(YEAR(STR_TO_DATE(`Date`, '%d/%m/%Y')), '-', MONTH(STR_TO_DATE(`Date`, '%d/%m/%Y'))), `Product`;",
            "Chart_SQL_Library": "MySQL",
            "Chart_Position": "1",
            "Chart_Type": "area_chart",
            "Chart_Title": "Revenue Generation vs Cost Efficiency and Product Profitability",
            "xAxis": "Revenue Generation",
            "xAxis_Description": "Revenue Generation",
            "X": [
                "2022-1",
                "2022-2",
                "2022-3",
                "2022-4",
                "2022-5",
                "2022-6",
                "2022-7",
                "2022-8",
                "2022-9",
                "2022-10",
                "2022-11",
                "2022-12",
                "2023-1",
                "2023-2",
                "2023-3",
                "2023-4",
                "2023-5",
                "2023-6",
                "2023-7",
                "2023-8",
                "2023-9",
                "2023-10",
                "2023-11",
                "2023-12"
            ],
            "yAxis": "Amount",
            "yAxis_Description": "Amount",
            "Y": [
                63.404052,
                58.023944,
                53.100662,
                48.594812,
                44.471344,
                40.697851,
                37.244682,
                34.08405,
                31.191999,
                28.545309,
                26.123097,
                23.906503,
                21.877991,
                20.021506,
                18.322623,
                16.767951,
                15.345151,
                14.043076,
                12.851436,
                11.760985,
                10.763005,
                9.849748,
                9.013954,
                8.249086
            ],
            "Y2": [
                65.306122,
                59.764478,
                54.693644,
                50.05213,
                45.805687,
                41.918309,
                38.361446,
                35.106722,
                32.127751,
                29.401529,
                26.90671,
                24.623593,
                22.534266,
                20.622175,
                18.872323,
                17.270965,
                15.805493,
                14.464351,
                13.23699,
                12.113773,
                11.085878,
                10.14522,
                9.284374,
                8.496539
            ],
            "Y3": [
                61.558201,
                56.334765,
                51.553539,
                47.179731,
                43.176553,
                39.512479,
                36.15989,
                33.09156,
                30.283425,
                27.714047,
                25.362368,
                23.210163,
                21.240892,
                19.438494,
                17.788997,
                16.27961,
                14.898217,
                13.634052,
                12.477174,
                11.418454,
                10.449564,
                9.562884,
                8.751428,
                8.008836
            ],
            "yName": "Average Cost Efficiency (BroadBand)",
            "y2Name": "Average Cost Efficiency (Entertainment)",
            "y3Name": "Average Cost Efficiency (Mobile)",
            "Smart_Insight": "No Description",
            "Business_Insight": "No Description",
            "Aggregated_Table_JSON": {
                "Subscription_ID": "",
                "Subscription_Name": "",
                "Client_ID": "starhub_001",
                "User_ID": "goldius.leo@userdata.tech",
                "Shared_User_ID": "",
                "Chart_Name": "Visual 3",
                "Chart_Axis": {},
                "Chart_Query": "SELECT      CONCAT(YEAR(STR_TO_DATE(`Date`, '%d/%m/%Y')), '-', MONTH(STR_TO_DATE(`Date`, '%d/%m/%Y'))) AS xAxis,      AVG(`Cost_Efficiency`) AS yAxis,      AVG(`Product_Profitability`) AS yAxis2,      `Product` AS series  FROM      starhub_data_asset.data_asset_001_pcc  GROUP BY      CONCAT(YEAR(STR_TO_DATE(`Date`, '%d/%m/%Y')), '-', MONTH(STR_TO_DATE(`Date`, '%d/%m/%Y'))), `Product`;",
                "Chart_SQL_Library": "MySQL",
                "Chart_Position": "1",
                "Chart_Type": "aggregated_table_chart",
                "Chart_Size": 664,
                "data": [
                    {
                        "Revenue Generation": "2022-1",
                        "Product": "BroadBand",
                        "Cost Efficiency": 63.404052,
                        "Product Profitability": 3.170818
                    },
                    {
                        "Revenue Generation": "2022-1",
                        "Product": "Entertainment",
                        "Cost Efficiency": 65.306122,
                        "Product Profitability": 3.265306
                    },
                    {
                        "Revenue Generation": "2022-1",
                        "Product": "Mobile",
                        "Cost Efficiency": 61.558201,
                        "Product Profitability": 2.903867
                    },
                    {
                        "Revenue Generation": "2022-2",
                        "Product": "Mobile",
                        "Cost Efficiency": 56.334765,
                        "Product Profitability": 2.507461
                    },
                    {
                        "Revenue Generation": "2022-2",
                        "Product": "Entertainment",
                        "Cost Efficiency": 59.764478,
                        "Product Profitability": 2.819711
                    },
                    {
                        "Revenue Generation": "2022-2",
                        "Product": "BroadBand",
                        "Cost Efficiency": 58.023944,
                        "Product Profitability": 2.582389
                    },
                    {
                        "Revenue Generation": "2022-3",
                        "Product": "Mobile",
                        "Cost Efficiency": 51.553539,
                        "Product Profitability": 2.042287
                    },
                    {
                        "Revenue Generation": "2022-3",
                        "Product": "BroadBand",
                        "Cost Efficiency": 53.100662,
                        "Product Profitability": 2.229762
                    },
                    {
                        "Revenue Generation": "2022-3",
                        "Product": "Entertainment",
                        "Cost Efficiency": 54.693644,
                        "Product Profitability": 2.296525
                    },
                    {
                        "Revenue Generation": "2022-4",
                        "Product": "Mobile",
                        "Cost Efficiency": 47.179731,
                        "Product Profitability": 1.763252
                    },
                    {
                        "Revenue Generation": "2022-4",
                        "Product": "Entertainment",
                        "Cost Efficiency": 50.05213,
                        "Product Profitability": 1.98284
                    },
                    {
                        "Revenue Generation": "2022-4",
                        "Product": "BroadBand",
                        "Cost Efficiency": 48.594812,
                        "Product Profitability": 1.816199
                    },
                    {
                        "Revenue Generation": "2022-5",
                        "Product": "Mobile",
                        "Cost Efficiency": 43.176553,
                        "Product Profitability": 1.436328
                    },
                    {
                        "Revenue Generation": "2022-5",
                        "Product": "Entertainment",
                        "Cost Efficiency": 45.805687,
                        "Product Profitability": 1.615137
                    },
                    {
                        "Revenue Generation": "2022-5",
                        "Product": "BroadBand",
                        "Cost Efficiency": 44.471344,
                        "Product Profitability": 1.568734
                    },
                    {
                        "Revenue Generation": "2022-6",
                        "Product": "Entertainment",
                        "Cost Efficiency": 41.918309,
                        "Product Profitability": 1.395
                    },
                    {
                        "Revenue Generation": "2022-6",
                        "Product": "Mobile",
                        "Cost Efficiency": 39.512479,
                        "Product Profitability": 1.240507
                    },
                    {
                        "Revenue Generation": "2022-6",
                        "Product": "BroadBand",
                        "Cost Efficiency": 40.697851,
                        "Product Profitability": 1.27731
                    },
                    {
                        "Revenue Generation": "2022-7",
                        "Product": "BroadBand",
                        "Cost Efficiency": 37.244682,
                        "Product Profitability": 1.10312
                    },
                    {
                        "Revenue Generation": "2022-7",
                        "Product": "Entertainment",
                        "Cost Efficiency": 38.361446,
                        "Product Profitability": 1.135892
                    },
                    {
                        "Revenue Generation": "2022-7",
                        "Product": "Mobile",
                        "Cost Efficiency": 36.15989,
                        "Product Profitability": 1.010136
                    },
                    {
                        "Revenue Generation": "2022-8",
                        "Product": "BroadBand",
                        "Cost Efficiency": 34.08405,
                        "Product Profitability": 0.898298
                    },
                    {
                        "Revenue Generation": "2022-8",
                        "Product": "Mobile",
                        "Cost Efficiency": 33.09156,
                        "Product Profitability": 0.872299
                    },
                    {
                        "Revenue Generation": "2022-8",
                        "Product": "Entertainment",
                        "Cost Efficiency": 35.106722,
                        "Product Profitability": 0.980944
                    },
                    {
                        "Revenue Generation": "2022-9",
                        "Product": "Mobile",
                        "Cost Efficiency": 30.283425,
                        "Product Profitability": 0.710391
                    },
                    {
                        "Revenue Generation": "2022-9",
                        "Product": "Entertainment",
                        "Cost Efficiency": 32.127751,
                        "Product Profitability": 0.798839
                    },
                    {
                        "Revenue Generation": "2022-9",
                        "Product": "BroadBand",
                        "Cost Efficiency": 31.191999,
                        "Product Profitability": 0.775687
                    },
                    {
                        "Revenue Generation": "2022-10",
                        "Product": "Mobile",
                        "Cost Efficiency": 27.714047,
                        "Product Profitability": 0.613374
                    },
                    {
                        "Revenue Generation": "2022-10",
                        "Product": "Entertainment",
                        "Cost Efficiency": 29.401529,
                        "Product Profitability": 0.689773
                    },
                    {
                        "Revenue Generation": "2022-10",
                        "Product": "BroadBand",
                        "Cost Efficiency": 28.545309,
                        "Product Profitability": 0.631735
                    },
                    {
                        "Revenue Generation": "2022-11",
                        "Product": "Mobile",
                        "Cost Efficiency": 25.362368,
                        "Product Profitability": 0.499583
                    },
                    {
                        "Revenue Generation": "2022-11",
                        "Product": "Entertainment",
                        "Cost Efficiency": 26.90671,
                        "Product Profitability": 0.561787
                    },
                    {
                        "Revenue Generation": "2022-11",
                        "Product": "BroadBand",
                        "Cost Efficiency": 26.123097,
                        "Product Profitability": 0.545434
                    },
                    {
                        "Revenue Generation": "2022-12",
                        "Product": "Entertainment",
                        "Cost Efficiency": 24.623593,
                        "Product Profitability": 0.48502
                    },
                    {
                        "Revenue Generation": "2022-12",
                        "Product": "BroadBand",
                        "Cost Efficiency": 23.906503,
                        "Product Profitability": 0.444265
                    },
                    {
                        "Revenue Generation": "2022-12",
                        "Product": "Mobile",
                        "Cost Efficiency": 23.210163,
                        "Product Profitability": 0.4315
                    },
                    {
                        "Revenue Generation": "2023-1",
                        "Product": "BroadBand",
                        "Cost Efficiency": 21.877991,
                        "Product Profitability": 0.383704
                    },
                    {
                        "Revenue Generation": "2023-1",
                        "Product": "Entertainment",
                        "Cost Efficiency": 22.534266,
                        "Product Profitability": 0.395071
                    },
                    {
                        "Revenue Generation": "2023-1",
                        "Product": "Mobile",
                        "Cost Efficiency": 21.240892,
                        "Product Profitability": 0.351325
                    },
                    {
                        "Revenue Generation": "2023-2",
                        "Product": "Mobile",
                        "Cost Efficiency": 19.438494,
                        "Product Profitability": 0.303405
                    },
                    {
                        "Revenue Generation": "2023-2",
                        "Product": "BroadBand",
                        "Cost Efficiency": 20.021506,
                        "Product Profitability": 0.312421
                    },
                    {
                        "Revenue Generation": "2023-2",
                        "Product": "Entertainment",
                        "Cost Efficiency": 20.622175,
                        "Product Profitability": 0.3412
                    },
                    {
                        "Revenue Generation": "2023-3",
                        "Product": "Mobile",
                        "Cost Efficiency": 17.788997,
                        "Product Profitability": 0.247059
                    },
                    {
                        "Revenue Generation": "2023-3",
                        "Product": "Entertainment",
                        "Cost Efficiency": 18.872323,
                        "Product Profitability": 0.277825
                    },
                    {
                        "Revenue Generation": "2023-3",
                        "Product": "BroadBand",
                        "Cost Efficiency": 18.322623,
                        "Product Profitability": 0.269796
                    },
                    {
                        "Revenue Generation": "2023-4",
                        "Product": "Entertainment",
                        "Cost Efficiency": 17.270965,
                        "Product Profitability": 0.239909
                    },
                    {
                        "Revenue Generation": "2023-4",
                        "Product": "BroadBand",
                        "Cost Efficiency": 16.767951,
                        "Product Profitability": 0.2197
                    },
                    {
                        "Revenue Generation": "2023-4",
                        "Product": "Mobile",
                        "Cost Efficiency": 16.27961,
                        "Product Profitability": 0.213332
                    },
                    {
                        "Revenue Generation": "2023-5",
                        "Product": "Mobile",
                        "Cost Efficiency": 14.898217,
                        "Product Profitability": 0.173735
                    },
                    {
                        "Revenue Generation": "2023-5",
                        "Product": "BroadBand",
                        "Cost Efficiency": 15.345151,
                        "Product Profitability": 0.1897
                    },
                    {
                        "Revenue Generation": "2023-5",
                        "Product": "Entertainment",
                        "Cost Efficiency": 15.805493,
                        "Product Profitability": 0.195371
                    },
                    {
                        "Revenue Generation": "2023-6",
                        "Product": "Mobile",
                        "Cost Efficiency": 13.634052,
                        "Product Profitability": 0.149997
                    },
                    {
                        "Revenue Generation": "2023-6",
                        "Product": "Entertainment",
                        "Cost Efficiency": 14.464351,
                        "Product Profitability": 0.168685
                    },
                    {
                        "Revenue Generation": "2023-6",
                        "Product": "BroadBand",
                        "Cost Efficiency": 14.043076,
                        "Product Profitability": 0.154494
                    },
                    {
                        "Revenue Generation": "2023-7",
                        "Product": "Entertainment",
                        "Cost Efficiency": 13.23699,
                        "Product Profitability": 0.137385
                    },
                    {
                        "Revenue Generation": "2023-7",
                        "Product": "BroadBand",
                        "Cost Efficiency": 12.851436,
                        "Product Profitability": 0.13338
                    },
                    {
                        "Revenue Generation": "2023-7",
                        "Product": "Mobile",
                        "Cost Efficiency": 12.477174,
                        "Product Profitability": 0.122169
                    },
                    {
                        "Revenue Generation": "2023-8",
                        "Product": "Entertainment",
                        "Cost Efficiency": 12.113773,
                        "Product Profitability": 0.118658
                    },
                    {
                        "Revenue Generation": "2023-8",
                        "Product": "BroadBand",
                        "Cost Efficiency": 11.760985,
                        "Product Profitability": 0.108639
                    },
                    {
                        "Revenue Generation": "2023-8",
                        "Product": "Mobile",
                        "Cost Efficiency": 11.418454,
                        "Product Profitability": 0.105513
                    },
                    {
                        "Revenue Generation": "2023-9",
                        "Product": "Entertainment",
                        "Cost Efficiency": 11.085878,
                        "Product Profitability": 0.096607
                    },
                    {
                        "Revenue Generation": "2023-9",
                        "Product": "Mobile",
                        "Cost Efficiency": 10.449564,
                        "Product Profitability": 0.085908
                    },
                    {
                        "Revenue Generation": "2023-9",
                        "Product": "BroadBand",
                        "Cost Efficiency": 10.763005,
                        "Product Profitability": 0.093823
                    },
                    {
                        "Revenue Generation": "2023-10",
                        "Product": "BroadBand",
                        "Cost Efficiency": 9.849748,
                        "Product Profitability": 0.076393
                    },
                    {
                        "Revenue Generation": "2023-10",
                        "Product": "Entertainment",
                        "Cost Efficiency": 10.14522,
                        "Product Profitability": 0.083428
                    },
                    {
                        "Revenue Generation": "2023-10",
                        "Product": "Mobile",
                        "Cost Efficiency": 9.562884,
                        "Product Profitability": 0.074185
                    },
                    {
                        "Revenue Generation": "2023-11",
                        "Product": "BroadBand",
                        "Cost Efficiency": 9.013954,
                        "Product Profitability": 0.065965
                    },
                    {
                        "Revenue Generation": "2023-11",
                        "Product": "Entertainment",
                        "Cost Efficiency": 9.284374,
                        "Product Profitability": 0.067932
                    },
                    {
                        "Revenue Generation": "2023-11",
                        "Product": "Mobile",
                        "Cost Efficiency": 8.751428,
                        "Product Profitability": 0.060408
                    },
                    {
                        "Revenue Generation": "2023-12",
                        "Product": "Mobile",
                        "Cost Efficiency": 8.008836,
                        "Product Profitability": 0.052158
                    },
                    {
                        "Revenue Generation": "2023-12",
                        "Product": "Entertainment",
                        "Cost Efficiency": 8.496539,
                        "Product Profitability": 0.058657
                    },
                    {
                        "Revenue Generation": "2023-12",
                        "Product": "BroadBand",
                        "Cost Efficiency": 8.249086,
                        "Product Profitability": 0.053717
                    }
                ],
                "Smart_Insight": "No Description",
                "Business_Insight": "No Description",
                "Database_Properties": {
                    "database_type": "mysql",
                    "database_name": "datalake",
                    "username": "AdaDB",
                    "password": "Admin@2024",
                    "hostname": "20.184.17.187",
                    "port": 3306,
                    "db_tag": "label1"
                }
            },
            "Aggregated_Table_Column": [
                "Revenue_Generation",
                "Cost_Efficiency",
                "Product_Profitability",
                "Product"
            ],
            "Database_Properties": {
                "database_type": "mysql",
                "database_name": "datalake",
                "username": "AdaDB",
                "password": "Admin@2024",
                "hostname": "20.184.17.187",
                "port": 3306,
                "db_tag": "label1"
            },
            "Y4": [
                3.170818,
                2.582389,
                2.229762,
                1.816199,
                1.568734,
                1.27731,
                1.10312,
                0.898298,
                0.775687,
                0.631735,
                0.545434,
                0.444265,
                0.383704,
                0.312421,
                0.269796,
                0.2197,
                0.1897,
                0.154494,
                0.13338,
                0.108639,
                0.093823,
                0.076393,
                0.065965,
                0.053717
            ],
            "y4Name": "Average Product Profitability (BroadBand)",
            "Y5": [
                3.265306,
                2.819711,
                2.296525,
                1.98284,
                1.615137,
                1.395,
                1.135892,
                0.980944,
                0.798839,
                0.689773,
                0.561787,
                0.48502,
                0.395071,
                0.3412,
                0.277825,
                0.239909,
                0.195371,
                0.168685,
                0.137385,
                0.118658,
                0.096607,
                0.083428,
                0.067932,
                0.058657
            ],
            "y5Name": "Average Product Profitability (Entertainment)",
            "Y6": [
                2.903867,
                2.507461,
                2.042287,
                1.763252,
                1.436328,
                1.240507,
                1.010136,
                0.872299,
                0.710391,
                0.613374,
                0.499583,
                0.4315,
                0.351325,
                0.303405,
                0.247059,
                0.213332,
                0.173735,
                0.149997,
                0.122169,
                0.105513,
                0.085908,
                0.074185,
                0.060408,
                0.052158
            ],
            "y6Name": "Average Product Profitability (Mobile)"
        },
        {
            "Subscription_ID": "",
            "Subscription_Name": "",
            "Client_ID": "starhub_001",
            "User_ID": "goldius.leo@userdata.tech",
            "Shared_User_ID": "",
            "Chart_Name": "Visual 3",
            "Chart_Axis": {
                "xAxis_title": "Month",
                "xAxis_column": "Date",
                "yAxis_title": "Total Revenue Generation",
                "yAxis_column": "Revenue_Generation",
                "yAxis_aggregation": "SUM",
                "yAxis2_title": "",
                "yAxis2_column": "",
                "yAxis2_aggregation": "",
                "yAxis3_title": "",
                "yAxis3_column": "",
                "yAxis3_aggregation": "",
                "series_title": "Product",
                "series_column": "Product"
            },
            "Chart_Query": "SELECT CONCAT(YEAR(STR_TO_DATE(Date, '%d/%m/%Y')), '-', MONTH(STR_TO_DATE(Date, '%d/%m/%Y'))) AS xAxis, SUM(Revenue_Generation) AS yAxis, Product AS series FROM starhub_data_asset.data_asset_001_pcc WHERE STR_TO_DATE(Date, '%d/%m/%Y') BETWEEN DATE_SUB(CURDATE(), INTERVAL 1 YEAR) AND CURDATE() GROUP BY xAxis, series ORDER BY xAxis;",
            "Chart_SQL_Library": "MySQL",
            "Chart_Position": "2",
            "Chart_Type": "grouped_column_chart",
            "Chart_Title": "Monthly Total Revenue Generation Trend by Product (Past Year)",
            "xAxis": "Month",
            "xAxis_Description": "Month",
            "X": [
                "2023-9",
                "2023-10",
                "2023-11",
                "2023-12"
            ],
            "yAxis": "Total Revenue Generation",
            "yAxis_Description": "Total Revenue Generation",
            "Y": [
                2295818.0,
                2743715.0,
                3278994.0,
                3918701.0
            ],
            "Y2": [
                2163401.0,
                2585464.0,
                3089869.0,
                3692680.0
            ],
            "Y3": [
                2436341.0,
                2911653.0,
                3479695.0,
                4158557.0
            ],
            "yName": "Total Revenue Generation (BroadBand)",
            "y2Name": "Total Revenue Generation (Entertainment)",
            "y3Name": "Total Revenue Generation (Mobile)",
            "Smart_Insight": "No Description",
            "Business_Insight": "No Description",
            "Aggregated_Table_JSON": {
                "Subscription_ID": "",
                "Subscription_Name": "",
                "Client_ID": "starhub_001",
                "User_ID": "goldius.leo@userdata.tech",
                "Shared_User_ID": "",
                "Chart_Name": "Visual 3",
                "Chart_Axis": {},
                "Chart_Query": "SELECT CONCAT(YEAR(STR_TO_DATE(Date, '%d/%m/%Y')), '-', MONTH(STR_TO_DATE(Date, '%d/%m/%Y'))) AS xAxis, SUM(Revenue_Generation) AS yAxis, Product AS series FROM starhub_data_asset.data_asset_001_pcc WHERE STR_TO_DATE(Date, '%d/%m/%Y') BETWEEN DATE_SUB(CURDATE(), INTERVAL 1 YEAR) AND CURDATE() GROUP BY xAxis, series ORDER BY xAxis;",
                "Chart_SQL_Library": "MySQL",
                "Chart_Position": "2",
                "Chart_Type": "aggregated_table_chart",
                "Chart_Size": 184,
                "data": [
                    {
                        "Month": "2023-9",
                        "Product": "BroadBand",
                        "Total Revenue Generation": 2295818.0
                    },
                    {
                        "Month": "2023-9",
                        "Product": "Entertainment",
                        "Total Revenue Generation": 2163401.0
                    },
                    {
                        "Month": "2023-9",
                        "Product": "Mobile",
                        "Total Revenue Generation": 2436341.0
                    },
                    {
                        "Month": "2023-10",
                        "Product": "BroadBand",
                        "Total Revenue Generation": 2743715.0
                    },
                    {
                        "Month": "2023-10",
                        "Product": "Entertainment",
                        "Total Revenue Generation": 2585464.0
                    },
                    {
                        "Month": "2023-10",
                        "Product": "Mobile",
                        "Total Revenue Generation": 2911653.0
                    },
                    {
                        "Month": "2023-11",
                        "Product": "BroadBand",
                        "Total Revenue Generation": 3278994.0
                    },
                    {
                        "Month": "2023-11",
                        "Product": "Entertainment",
                        "Total Revenue Generation": 3089869.0
                    },
                    {
                        "Month": "2023-11",
                        "Product": "Mobile",
                        "Total Revenue Generation": 3479695.0
                    },
                    {
                        "Month": "2023-12",
                        "Product": "BroadBand",
                        "Total Revenue Generation": 3918701.0
                    },
                    {
                        "Month": "2023-12",
                        "Product": "Entertainment",
                        "Total Revenue Generation": 3692680.0
                    },
                    {
                        "Month": "2023-12",
                        "Product": "Mobile",
                        "Total Revenue Generation": 4158557.0
                    }
                ],
                "Smart_Insight": "No Description",
                "Business_Insight": "No Description",
                "Database_Properties": {
                    "database_type": "mysql",
                    "database_name": "datalake",
                    "username": "AdaDB",
                    "password": "Admin@2024",
                    "hostname": "20.184.17.187",
                    "port": 3306,
                    "db_tag": "label1"
                }
            },
            "Aggregated_Table_Column": [
                "Revenue_Generation",
                "Product",
                "Date"
            ],
            "Database_Properties": {
                "database_type": "mysql",
                "database_name": "datalake",
                "username": "AdaDB",
                "password": "Admin@2024",
                "hostname": "20.184.17.187",
                "port": 3306,
                "db_tag": "label1"
            }
        },
        {
            "Subscription_ID": "",
            "Subscription_Name": "",
            "Client_ID": "starhub_001",
            "User_ID": "goldius.leo@userdata.tech",
            "Shared_User_ID": "",
            "Chart_Name": "Visual 3",
            "Chart_Axis": {
                "xAxis_title": "Month",
                "xAxis_column": "Date",
                "yAxis_title": "Average Cost Efficiency",
                "yAxis_column": "Cost_Efficiency",
                "yAxis_aggregation": "AVG",
                "yAxis2_title": "",
                "yAxis2_column": "",
                "yAxis2_aggregation": "",
                "yAxis3_title": "",
                "yAxis3_column": "",
                "yAxis3_aggregation": "",
                "series_title": "Product",
                "series_column": "Product"
            },
            "Chart_Query": "SELECT CONCAT(YEAR(STR_TO_DATE(Date, '%d/%m/%Y')), '-', MONTH(STR_TO_DATE(Date, '%d/%m/%Y'))) AS xAxis, AVG(Cost_Efficiency) AS yAxis, Product AS series FROM starhub_data_asset.data_asset_001_pcc WHERE STR_TO_DATE(Date, '%d/%m/%Y') BETWEEN DATE_SUB(CURDATE(), INTERVAL 1 YEAR) AND CURDATE() GROUP BY xAxis, series ORDER BY xAxis;",
            "Chart_SQL_Library": "MySQL",
            "Chart_Position": "3",
            "Chart_Type": "line_chart",
            "Chart_Title": "Monthly Average Cost Efficiency Trend by Product (Past Year)",
            "xAxis": "Month",
            "xAxis_Description": "Month",
            "X": [
                "2023-9",
                "2023-10",
                "2023-11",
                "2023-12"
            ],
            "yAxis": "Average Cost Efficiency",
            "yAxis_Description": "Average Cost Efficiency",
            "Y": [
                10.763005,
                9.849748,
                9.013954,
                8.249086
            ],
            "Y2": [
                11.085878,
                10.14522,
                9.284374,
                8.496539
            ],
            "Y3": [
                10.449564,
                9.562884,
                8.751428,
                8.008836
            ],
            "yName": "Average Cost Efficiency (BroadBand)",
            "y2Name": "Average Cost Efficiency (Entertainment)",
            "y3Name": "Average Cost Efficiency (Mobile)",
            "Smart_Insight": "No Description",
            "Business_Insight": "No Description",
            "Aggregated_Table_JSON": {
                "Subscription_ID": "",
                "Subscription_Name": "",
                "Client_ID": "starhub_001",
                "User_ID": "goldius.leo@userdata.tech",
                "Shared_User_ID": "",
                "Chart_Name": "Visual 3",
                "Chart_Axis": {},
                "Chart_Query": "SELECT CONCAT(YEAR(STR_TO_DATE(Date, '%d/%m/%Y')), '-', MONTH(STR_TO_DATE(Date, '%d/%m/%Y'))) AS xAxis, AVG(Cost_Efficiency) AS yAxis, Product AS series FROM starhub_data_asset.data_asset_001_pcc WHERE STR_TO_DATE(Date, '%d/%m/%Y') BETWEEN DATE_SUB(CURDATE(), INTERVAL 1 YEAR) AND CURDATE() GROUP BY xAxis, series ORDER BY xAxis;",
                "Chart_SQL_Library": "MySQL",
                "Chart_Position": "3",
                "Chart_Type": "aggregated_table_chart",
                "Chart_Size": 184,
                "data": [
                    {
                        "Month": "2023-9",
                        "Product": "BroadBand",
                        "Average Cost Efficiency": 10.763005
                    },
                    {
                        "Month": "2023-9",
                        "Product": "Entertainment",
                        "Average Cost Efficiency": 11.085878
                    },
                    {
                        "Month": "2023-9",
                        "Product": "Mobile",
                        "Average Cost Efficiency": 10.449564
                    },
                    {
                        "Month": "2023-10",
                        "Product": "BroadBand",
                        "Average Cost Efficiency": 9.849748
                    },
                    {
                        "Month": "2023-10",
                        "Product": "Entertainment",
                        "Average Cost Efficiency": 10.14522
                    },
                    {
                        "Month": "2023-10",
                        "Product": "Mobile",
                        "Average Cost Efficiency": 9.562884
                    },
                    {
                        "Month": "2023-11",
                        "Product": "BroadBand",
                        "Average Cost Efficiency": 9.013954
                    },
                    {
                        "Month": "2023-11",
                        "Product": "Entertainment",
                        "Average Cost Efficiency": 9.284374
                    },
                    {
                        "Month": "2023-11",
                        "Product": "Mobile",
                        "Average Cost Efficiency": 8.751428
                    },
                    {
                        "Month": "2023-12",
                        "Product": "BroadBand",
                        "Average Cost Efficiency": 8.249086
                    },
                    {
                        "Month": "2023-12",
                        "Product": "Entertainment",
                        "Average Cost Efficiency": 8.496539
                    },
                    {
                        "Month": "2023-12",
                        "Product": "Mobile",
                        "Average Cost Efficiency": 8.008836
                    }
                ],
                "Smart_Insight": "No Description",
                "Business_Insight": "No Description",
                "Database_Properties": {
                    "database_type": "mysql",
                    "database_name": "datalake",
                    "username": "AdaDB",
                    "password": "Admin@2024",
                    "hostname": "20.184.17.187",
                    "port": 3306,
                    "db_tag": "label1"
                }
            },
            "Aggregated_Table_Column": [
                "Product",
                "Cost_Efficiency",
                "Date"
            ],
            "Database_Properties": {
                "database_type": "mysql",
                "database_name": "datalake",
                "username": "AdaDB",
                "password": "Admin@2024",
                "hostname": "20.184.17.187",
                "port": 3306,
                "db_tag": "label1"
            }
        },
        {
            "Subscription_ID": "",
            "Subscription_Name": "",
            "Client_ID": "starhub_001",
            "User_ID": "goldius.leo@userdata.tech",
            "Shared_User_ID": "",
            "Chart_Name": "Table",
            "Visual_Title": "Data Asset Table",
            "Chart_Axis": {},
            "Chart_Query": "SELECT * FROM `starhub_data_asset`.`data_asset_001_pcc`;",
            "Chart_SQL_Library": "MySQL",
            "Chart_Position": "1",
            "Chart_Type": "full_table_chart",
            "Chart_Title": "Data Asset Table",
            "Chart_Size": 664,
            "data": [
                {
                    "Product": "BroadBand",
                    "Date": "01/09/2023",
                    "Revenue_Generation": 2295818,
                    "Cost_Efficiency": 10.763005,
                    "Product_Profitability": 0.093823
                },
                {
                    "Product": "BroadBand",
                    "Date": "01/05/2023",
                    "Revenue_Generation": 1125463,
                    "Cost_Efficiency": 15.345151,
                    "Product_Profitability": 0.1897
                },
                {
                    "Product": "BroadBand",
                    "Date": "01/07/2023",
                    "Revenue_Generation": 1607439,
                    "Cost_Efficiency": 12.851436,
                    "Product_Profitability": 0.13338
                },
                {
                    "Product": "BroadBand",
                    "Date": "01/04/2023",
                    "Revenue_Generation": 941737,
                    "Cost_Efficiency": 16.767951,
                    "Product_Profitability": 0.2197
                },
                {
                    "Product": "BroadBand",
                    "Date": "01/03/2023",
                    "Revenue_Generation": 788004,
                    "Cost_Efficiency": 18.322623,
                    "Product_Profitability": 0.269796
                },
                {
                    "Product": "BroadBand",
                    "Date": "01/02/2023",
                    "Revenue_Generation": 659366,
                    "Cost_Efficiency": 20.021506,
                    "Product_Profitability": 0.312421
                },
                {
                    "Product": "BroadBand",
                    "Date": "01/08/2023",
                    "Revenue_Generation": 1921038,
                    "Cost_Efficiency": 11.760985,
                    "Product_Profitability": 0.108639
                },
                {
                    "Product": "BroadBand",
                    "Date": "01/01/2023",
                    "Revenue_Generation": 551728,
                    "Cost_Efficiency": 21.877991,
                    "Product_Profitability": 0.383704
                },
                {
                    "Product": "BroadBand",
                    "Date": "01/12/2023",
                    "Revenue_Generation": 3918701,
                    "Cost_Efficiency": 8.249086,
                    "Product_Profitability": 0.053717
                },
                {
                    "Product": "BroadBand",
                    "Date": "01/12/2022",
                    "Revenue_Generation": 461661,
                    "Cost_Efficiency": 23.906503,
                    "Product_Profitability": 0.444265
                },
                {
                    "Product": "BroadBand",
                    "Date": "01/11/2022",
                    "Revenue_Generation": 386298,
                    "Cost_Efficiency": 26.123097,
                    "Product_Profitability": 0.545434
                },
                {
                    "Product": "BroadBand",
                    "Date": "01/10/2022",
                    "Revenue_Generation": 323237,
                    "Cost_Efficiency": 28.545309,
                    "Product_Profitability": 0.631735
                },
                {
                    "Product": "BroadBand",
                    "Date": "01/09/2022",
                    "Revenue_Generation": 270470,
                    "Cost_Efficiency": 31.191999,
                    "Product_Profitability": 0.775687
                },
                {
                    "Product": "BroadBand",
                    "Date": "01/08/2022",
                    "Revenue_Generation": 226317,
                    "Cost_Efficiency": 34.08405,
                    "Product_Profitability": 0.898298
                },
                {
                    "Product": "BroadBand",
                    "Date": "01/07/2022",
                    "Revenue_Generation": 189372,
                    "Cost_Efficiency": 37.244682,
                    "Product_Profitability": 1.10312
                },
                {
                    "Product": "BroadBand",
                    "Date": "01/10/2023",
                    "Revenue_Generation": 2743715,
                    "Cost_Efficiency": 9.849748,
                    "Product_Profitability": 0.076393
                },
                {
                    "Product": "BroadBand",
                    "Date": "01/06/2023",
                    "Revenue_Generation": 1345033,
                    "Cost_Efficiency": 14.043076,
                    "Product_Profitability": 0.154494
                },
                {
                    "Product": "BroadBand",
                    "Date": "01/02/2022",
                    "Revenue_Generation": 77680,
                    "Cost_Efficiency": 58.023944,
                    "Product_Profitability": 2.582389
                },
                {
                    "Product": "BroadBand",
                    "Date": "01/04/2022",
                    "Revenue_Generation": 110946,
                    "Cost_Efficiency": 48.594812,
                    "Product_Profitability": 1.816199
                },
                {
                    "Product": "BroadBand",
                    "Date": "01/03/2022",
                    "Revenue_Generation": 92835,
                    "Cost_Efficiency": 53.100662,
                    "Product_Profitability": 2.229762
                },
                {
                    "Product": "BroadBand",
                    "Date": "01/11/2023",
                    "Revenue_Generation": 3278994,
                    "Cost_Efficiency": 9.013954,
                    "Product_Profitability": 0.065965
                },
                {
                    "Product": "BroadBand",
                    "Date": "01/05/2022",
                    "Revenue_Generation": 132591,
                    "Cost_Efficiency": 44.471344,
                    "Product_Profitability": 1.568734
                },
                {
                    "Product": "BroadBand",
                    "Date": "01/06/2022",
                    "Revenue_Generation": 158458,
                    "Cost_Efficiency": 40.697851,
                    "Product_Profitability": 1.27731
                },
                {
                    "Product": "BroadBand",
                    "Date": "01/01/2022",
                    "Revenue_Generation": 64999,
                    "Cost_Efficiency": 63.404052,
                    "Product_Profitability": 3.170818
                },
                {
                    "Product": "Entertainment",
                    "Date": "01/02/2022",
                    "Revenue_Generation": 73199,
                    "Cost_Efficiency": 59.764478,
                    "Product_Profitability": 2.819711
                },
                {
                    "Product": "Entertainment",
                    "Date": "01/04/2023",
                    "Revenue_Generation": 887420,
                    "Cost_Efficiency": 17.270965,
                    "Product_Profitability": 0.239909
                },
                {
                    "Product": "Entertainment",
                    "Date": "01/05/2023",
                    "Revenue_Generation": 1060549,
                    "Cost_Efficiency": 15.805493,
                    "Product_Profitability": 0.195371
                },
                {
                    "Product": "Entertainment",
                    "Date": "01/03/2023",
                    "Revenue_Generation": 742553,
                    "Cost_Efficiency": 18.872323,
                    "Product_Profitability": 0.277825
                },
                {
                    "Product": "Entertainment",
                    "Date": "01/08/2023",
                    "Revenue_Generation": 1810237,
                    "Cost_Efficiency": 12.113773,
                    "Product_Profitability": 0.118658
                },
                {
                    "Product": "Entertainment",
                    "Date": "01/02/2023",
                    "Revenue_Generation": 621336,
                    "Cost_Efficiency": 20.622175,
                    "Product_Profitability": 0.3412
                },
                {
                    "Product": "Entertainment",
                    "Date": "01/03/2022",
                    "Revenue_Generation": 87480,
                    "Cost_Efficiency": 54.693644,
                    "Product_Profitability": 2.296525
                },
                {
                    "Product": "Entertainment",
                    "Date": "01/07/2023",
                    "Revenue_Generation": 1514725,
                    "Cost_Efficiency": 13.23699,
                    "Product_Profitability": 0.137385
                },
                {
                    "Product": "Entertainment",
                    "Date": "01/01/2023",
                    "Revenue_Generation": 519906,
                    "Cost_Efficiency": 22.534266,
                    "Product_Profitability": 0.395071
                },
                {
                    "Product": "Entertainment",
                    "Date": "01/12/2023",
                    "Revenue_Generation": 3692680,
                    "Cost_Efficiency": 8.496539,
                    "Product_Profitability": 0.058657
                },
                {
                    "Product": "Entertainment",
                    "Date": "01/06/2022",
                    "Revenue_Generation": 149319,
                    "Cost_Efficiency": 41.918309,
                    "Product_Profitability": 1.395
                },
                {
                    "Product": "Entertainment",
                    "Date": "01/04/2022",
                    "Revenue_Generation": 104547,
                    "Cost_Efficiency": 50.05213,
                    "Product_Profitability": 1.98284
                },
                {
                    "Product": "Entertainment",
                    "Date": "01/01/2022",
                    "Revenue_Generation": 61250,
                    "Cost_Efficiency": 65.306122,
                    "Product_Profitability": 3.265306
                },
                {
                    "Product": "Entertainment",
                    "Date": "01/11/2022",
                    "Revenue_Generation": 364017,
                    "Cost_Efficiency": 26.90671,
                    "Product_Profitability": 0.561787
                },
                {
                    "Product": "Entertainment",
                    "Date": "01/09/2023",
                    "Revenue_Generation": 2163401,
                    "Cost_Efficiency": 11.085878,
                    "Product_Profitability": 0.096607
                },
                {
                    "Product": "Entertainment",
                    "Date": "01/11/2023",
                    "Revenue_Generation": 3089869,
                    "Cost_Efficiency": 9.284374,
                    "Product_Profitability": 0.067932
                },
                {
                    "Product": "Entertainment",
                    "Date": "01/07/2022",
                    "Revenue_Generation": 178450,
                    "Cost_Efficiency": 38.361446,
                    "Product_Profitability": 1.135892
                },
                {
                    "Product": "Entertainment",
                    "Date": "01/10/2022",
                    "Revenue_Generation": 304593,
                    "Cost_Efficiency": 29.401529,
                    "Product_Profitability": 0.689773
                },
                {
                    "Product": "Entertainment",
                    "Date": "01/06/2023",
                    "Revenue_Generation": 1267454,
                    "Cost_Efficiency": 14.464351,
                    "Product_Profitability": 0.168685
                },
                {
                    "Product": "Entertainment",
                    "Date": "01/05/2022",
                    "Revenue_Generation": 124943,
                    "Cost_Efficiency": 45.805687,
                    "Product_Profitability": 1.615137
                },
                {
                    "Product": "Entertainment",
                    "Date": "01/12/2022",
                    "Revenue_Generation": 435034,
                    "Cost_Efficiency": 24.623593,
                    "Product_Profitability": 0.48502
                },
                {
                    "Product": "Entertainment",
                    "Date": "01/09/2022",
                    "Revenue_Generation": 254870,
                    "Cost_Efficiency": 32.127751,
                    "Product_Profitability": 0.798839
                },
                {
                    "Product": "Entertainment",
                    "Date": "01/08/2022",
                    "Revenue_Generation": 213264,
                    "Cost_Efficiency": 35.106722,
                    "Product_Profitability": 0.980944
                },
                {
                    "Product": "Entertainment",
                    "Date": "01/10/2023",
                    "Revenue_Generation": 2585464,
                    "Cost_Efficiency": 10.14522,
                    "Product_Profitability": 0.083428
                },
                {
                    "Product": "Mobile",
                    "Date": "01/10/2023",
                    "Revenue_Generation": 2911653,
                    "Cost_Efficiency": 9.562884,
                    "Product_Profitability": 0.074185
                },
                {
                    "Product": "Mobile",
                    "Date": "01/08/2023",
                    "Revenue_Generation": 2038621,
                    "Cost_Efficiency": 11.418454,
                    "Product_Profitability": 0.105513
                },
                {
                    "Product": "Mobile",
                    "Date": "01/11/2023",
                    "Revenue_Generation": 3479695,
                    "Cost_Efficiency": 8.751428,
                    "Product_Profitability": 0.060408
                },
                {
                    "Product": "Mobile",
                    "Date": "01/09/2023",
                    "Revenue_Generation": 2436341,
                    "Cost_Efficiency": 10.449564,
                    "Product_Profitability": 0.085908
                },
                {
                    "Product": "Mobile",
                    "Date": "01/07/2023",
                    "Revenue_Generation": 1705827,
                    "Cost_Efficiency": 12.477174,
                    "Product_Profitability": 0.122169
                },
                {
                    "Product": "Mobile",
                    "Date": "01/12/2022",
                    "Revenue_Generation": 489919,
                    "Cost_Efficiency": 23.210163,
                    "Product_Profitability": 0.4315
                },
                {
                    "Product": "Mobile",
                    "Date": "01/05/2023",
                    "Revenue_Generation": 1194351,
                    "Cost_Efficiency": 14.898217,
                    "Product_Profitability": 0.173735
                },
                {
                    "Product": "Mobile",
                    "Date": "01/01/2022",
                    "Revenue_Generation": 68977,
                    "Cost_Efficiency": 61.558201,
                    "Product_Profitability": 2.903867
                },
                {
                    "Product": "Mobile",
                    "Date": "01/02/2022",
                    "Revenue_Generation": 82434,
                    "Cost_Efficiency": 56.334765,
                    "Product_Profitability": 2.507461
                },
                {
                    "Product": "Mobile",
                    "Date": "01/03/2022",
                    "Revenue_Generation": 98517,
                    "Cost_Efficiency": 51.553539,
                    "Product_Profitability": 2.042287
                },
                {
                    "Product": "Mobile",
                    "Date": "01/04/2022",
                    "Revenue_Generation": 117737,
                    "Cost_Efficiency": 47.179731,
                    "Product_Profitability": 1.763252
                },
                {
                    "Product": "Mobile",
                    "Date": "01/05/2022",
                    "Revenue_Generation": 140706,
                    "Cost_Efficiency": 43.176553,
                    "Product_Profitability": 1.436328
                },
                {
                    "Product": "Mobile",
                    "Date": "01/06/2022",
                    "Revenue_Generation": 168157,
                    "Cost_Efficiency": 39.512479,
                    "Product_Profitability": 1.240507
                },
                {
                    "Product": "Mobile",
                    "Date": "01/07/2022",
                    "Revenue_Generation": 200963,
                    "Cost_Efficiency": 36.15989,
                    "Product_Profitability": 1.010136
                },
                {
                    "Product": "Mobile",
                    "Date": "01/08/2022",
                    "Revenue_Generation": 240170,
                    "Cost_Efficiency": 33.09156,
                    "Product_Profitability": 0.872299
                },
                {
                    "Product": "Mobile",
                    "Date": "01/09/2022",
                    "Revenue_Generation": 287025,
                    "Cost_Efficiency": 30.283425,
                    "Product_Profitability": 0.710391
                },
                {
                    "Product": "Mobile",
                    "Date": "01/10/2022",
                    "Revenue_Generation": 343021,
                    "Cost_Efficiency": 27.714047,
                    "Product_Profitability": 0.613374
                },
                {
                    "Product": "Mobile",
                    "Date": "01/11/2022",
                    "Revenue_Generation": 409942,
                    "Cost_Efficiency": 25.362368,
                    "Product_Profitability": 0.499583
                },
                {
                    "Product": "Mobile",
                    "Date": "01/01/2023",
                    "Revenue_Generation": 585498,
                    "Cost_Efficiency": 21.240892,
                    "Product_Profitability": 0.351325
                },
                {
                    "Product": "Mobile",
                    "Date": "01/02/2023",
                    "Revenue_Generation": 699725,
                    "Cost_Efficiency": 19.438494,
                    "Product_Profitability": 0.303405
                },
                {
                    "Product": "Mobile",
                    "Date": "01/03/2023",
                    "Revenue_Generation": 836236,
                    "Cost_Efficiency": 17.788997,
                    "Product_Profitability": 0.247059
                },
                {
                    "Product": "Mobile",
                    "Date": "01/04/2023",
                    "Revenue_Generation": 999379,
                    "Cost_Efficiency": 16.27961,
                    "Product_Profitability": 0.213332
                },
                {
                    "Product": "Mobile",
                    "Date": "01/06/2023",
                    "Revenue_Generation": 1427360,
                    "Cost_Efficiency": 13.634052,
                    "Product_Profitability": 0.149997
                },
                {
                    "Product": "Mobile",
                    "Date": "01/12/2023",
                    "Revenue_Generation": 4158557,
                    "Cost_Efficiency": 8.008836,
                    "Product_Profitability": 0.052158
                }
            ],
            "Smart_Insight": "No Description",
            "Business_Insight": "No Description",
            "Database_Properties": {
                "db_tag": "MySQL",
                "hostname": "20.184.17.187",
                "username": "AdaDB",
                "password": "Admin@2024",
                "port": 3306
            }
        }
    ],
    "Inference_Time": 509.5,
    "Inference_Time_To_First_Chart": 228.87,
    "Valid_SQL_Query_Rate": 28.57,
    "Valid_JSON_Rate": 28.57
}